{"Thierry Baudet": {"lijstnummer": 1, "kieskringen": ["Bonaire"], "naam": "Thierry Baudet", "achternaam": "Baudet", "voorletters": "T.H.P.", "voornaam": "Thierry", "geslacht": "m", "stad": "Amsterdam", "partij_naam": "Forum voor Democratie", "tweede_poging": false, "vorige_partij": "", "vorige_woonplaats": "", "links": []}, "Theo Hiddema": {"lijstnummer": 2, "kieskringen": ["Bonaire"], "naam": "Theo Hiddema", "achternaam": "Hiddema", "voorletters": "T.U.", "voornaam": "Theo", "geslacht": "m", "stad": "Maastricht", "partij_naam": "Forum voor Democratie", "tweede_poging": false, "vorige_partij": "", "vorige_woonplaats": "", "links": []}, "Susan Teunissen": {"lijstnummer": 3, "kieskringen": ["Bonaire"], "naam": "Susan Teunissen", "achternaam": "Teunissen", "voorletters": "S.M.", "voornaam": "Susan", "geslacht": "v", "stad": "Utrecht", "partij_naam": "Forum voor Democratie", "tweede_poging": false, "vorige_partij": "", "vorige_woonplaats": "", "links": []}, "Henk Otten": {"lijstnummer": 4, "kieskringen": ["Bonaire"], "naam": "Henk Otten", "achternaam": "Otten", "voorletters": "H.", "voornaam": "Henk", "geslacht": "m", "stad": "Amsterdam", "partij_naam": "Forum voor Democratie", "tweede_poging": false, "vorige_partij": "", "vorige_woonplaats": "", "links": []}, "Paul Frentrop": {"lijstnummer": 5, "kieskringen": ["Bonaire"], "naam": "Paul Frentrop", "achternaam": "Frentrop", "voorletters": "P.M.L.", "voornaam": "Paul", "geslacht": "m", "stad": "Bloemendaal", "partij_naam": "Forum voor Democratie", "tweede_poging": false, "vorige_partij": "", "vorige_woonplaats": "", "links": []}, "Rob Rooken": {"lijstnummer": 6, "kieskringen": ["Bonaire"], "naam": "Rob Rooken", "achternaam": "Rooken", "voorletters": "R.J.", "voornaam": "Rob", "geslacht": "m", "stad": "Muiderberg", "partij_naam": "Forum voor Democratie", "tweede_poging": false, "vorige_partij": "", "vorige_woonplaats": "", "links": []}, "Susan Stolze - van Rijn": {"lijstnummer": 7, "kieskringen": ["Bonaire"], "naam": "Susan Stolze - van Rijn", "achternaam": "Stolze - van Rijn", "voorletters": "S.E.", "voornaam": "Susan", "geslacht": "v", "stad": "Rotterdam", "partij_naam": "Forum voor Democratie", "tweede_poging": false, "vorige_partij": "", "vorige_woonplaats": "", "links": []}, "Gert Reedijk": {"lijstnummer": 8, "kieskringen": ["Bonaire"], "naam": "Gert Reedijk", "achternaam": "Reedijk", "voorletters": "G.P.", "voornaam": "Gert", "geslacht": "m", "stad": "Zwolle", "partij_naam": "Forum voor Democratie", "tweede_poging": false, "vorige_partij": "", "vorige_woonplaats": "", "links": []}, "Yernaz Ramautarsing": {"lijstnummer": 9, "kieskringen": ["Bonaire"], "naam": "Yernaz Ramautarsing", "achternaam": "Ramautarsing", "voorletters": "Y.J.S.", "voornaam": "Yernaz", "geslacht": "m", "stad": "Amsterdam", "partij_naam": "Forum voor Democratie", "tweede_poging": false, "vorige_partij": "", "vorige_woonplaats": "", "links": []}, "Zlata Brouwer": {"lijstnummer": 10, "kieskringen": ["Bonaire"], "naam": "Zlata Brouwer", "achternaam": "Brouwer", "voorletters": "Z.M.A.", "voornaam": "Zlata", "geslacht": "v", "stad": "Hilversum", "partij_naam": "Forum voor Democratie", "tweede_poging": false, "vorige_partij": "", "vorige_woonplaats": "", "links": []}, "Jeroen de Vries": {"lijstnummer": 11, "kieskringen": ["Bonaire"], "naam": "Jeroen de Vries", "achternaam": "de Vries", "voorletters": "J.W.E.", "voornaam": "Jeroen", "geslacht": "m", "stad": "Amsterdam", "partij_naam": "Forum voor Democratie", "tweede_poging": false, "vorige_partij": "", "vorige_woonplaats": "", "links": []}, "Arthur Legger": {"lijstnummer": 12, "kieskringen": ["Bonaire"], "naam": "Arthur Legger", "achternaam": "Legger", "voorletters": "A.L.", "voornaam": "Arthur", "geslacht": "m", "stad": "Amsterdam", "partij_naam": "Forum voor Democratie", "tweede_poging": false, "vorige_partij": "", "vorige_woonplaats": "", "links": []}, "Carola Dieudonné": {"lijstnummer": 13, "kieskringen": ["Bonaire"], "naam": "Carola Dieudonné", "achternaam": "Dieudonné", "voorletters": "C.A.", "voornaam": "Carola", "geslacht": "v", "stad": "'s-Gravenhage", "partij_naam": "Forum voor Democratie", "tweede_poging": false, "vorige_partij": "", "vorige_woonplaats": "", "links": []}, "Godert van Assen": {"lijstnummer": 14, "kieskringen": ["Bonaire"], "naam": "Godert van Assen", "achternaam": "van Assen", "voorletters": "G.J.E.", "voornaam": "Godert", "geslacht": "m", "stad": "Bussum", "partij_naam": "Forum voor Democratie", "tweede_poging": false, "vorige_partij": "", "vorige_woonplaats": "", "links": []}, "Geert Jeelof": {"lijstnummer": 15, "kieskringen": ["Bonaire"], "naam": "Geert Jeelof", "achternaam": "Jeelof", "voorletters": "G.W.D.", "voornaam": "Geert", "geslacht": "m", "stad": "Oud-Beijerland", "partij_naam": "Forum voor Democratie", "tweede_poging": false, "vorige_partij": "", "vorige_woonplaats": "", "links": []}, "Luke Boltjes": {"lijstnummer": 16, "kieskringen": ["Bonaire"], "naam": "Luke Boltjes", "achternaam": "Boltjes", "voorletters": "L.", "voornaam": "Luke", "geslacht": "m", "stad": "Scheemda", "partij_naam": "Forum voor Democratie", "tweede_poging": false, "vorige_partij": "", "vorige_woonplaats": "", "links": []}, "F.J. Berkhout": {"lijstnummer": 17, "kieskringen": ["Groningen", "Leeuwarden", "Assen", "Zwolle", "Lelystad", "Nijmegen", "Arnhem", "Utrecht", "Amsterdam", "Haarlem", "Den Helder", "'s-Gravenhage", "Rotterdam", "Dordrecht", "Leiden", "Middelburg", "Tilburg", "'s-Hertogenbosch", "Maastricht", "Bonaire"], "naam": "F.J. Berkhout", "achternaam": "Berkhout", "voorletters": "F.J.", "voornaam": "", "geslacht": "m", "stad": "Utrechtse Heuvelrug", "partij_naam": "Forum voor Democratie", "tweede_poging": false, "vorige_partij": "", "vorige_woonplaats": "", "links": []}, "Sander Boon": {"lijstnummer": 18, "kieskringen": ["Bonaire"], "naam": "Sander Boon", "achternaam": "Boon", "voorletters": "S.O.", "voornaam": "Sander", "geslacht": "m", "stad": "Amsterdam", "partij_naam": "Forum voor Democratie", "tweede_poging": false, "vorige_partij": "", "vorige_woonplaats": "", "links": []}, "Arjan de Kok": {"lijstnummer": 19, "kieskringen": ["Bonaire"], "naam": "Arjan de Kok", "achternaam": "de Kok", "voorletters": "A.", "voornaam": "Arjan", "geslacht": "m", "stad": "Noordeinde Gld", "partij_naam": "Forum voor Democratie", "tweede_poging": false, "vorige_partij": "", "vorige_woonplaats": "", "links": []}, "Astrid de Groot": {"lijstnummer": 20, "kieskringen": ["Bonaire"], "naam": "Astrid de Groot", "achternaam": "de Groot", "voorletters": "A.R.", "voornaam": "Astrid", "geslacht": "v", "stad": "Heukelum", "partij_naam": "Forum voor Democratie", "tweede_poging": false, "vorige_partij": "", "vorige_woonplaats": "", "links": []}, "Hugo Berkhout": {"lijstnummer": 21, "kieskringen": ["Bonaire"], "naam": "Hugo Berkhout", "achternaam": "Berkhout", "voorletters": "H.A.", "voornaam": "Hugo", "geslacht": "m", "stad": "Amsterdam", "partij_naam": "Forum voor Democratie", "tweede_poging": false, "vorige_partij": "", "vorige_woonplaats": "", "links": []}, "Roel Mooijekind": {"lijstnummer": 22, "kieskringen": ["Bonaire"], "naam": "Roel Mooijekind", "achternaam": "Mooijekind", "voorletters": "R.A.", "voornaam": "Roel", "geslacht": "m", "stad": "Alkmaar", "partij_naam": "Forum voor Democratie", "tweede_poging": false, "vorige_partij": "", "vorige_woonplaats": "", "links": []}, "Kees Eldering": {"lijstnummer": 23, "kieskringen": ["Bonaire"], "naam": "Kees Eldering", "achternaam": "Eldering", "voorletters": "C.H.", "voornaam": "Kees", "geslacht": "m", "stad": "Roderwolde", "partij_naam": "Forum voor Democratie", "tweede_poging": false, "vorige_partij": "", "vorige_woonplaats": "", "links": []}, "Erik Verbrugh": {"lijstnummer": 24, "kieskringen": ["Bonaire"], "naam": "Erik Verbrugh", "achternaam": "Verbrugh", "voorletters": "D.J.", "voornaam": "Erik", "geslacht": "m", "stad": "Woerden", "partij_naam": "Forum voor Democratie", "tweede_poging": false, "vorige_partij": "", "vorige_woonplaats": "", "links": []}, "Saskia Koning": {"lijstnummer": 25, "kieskringen": ["Bonaire"], "naam": "Saskia Koning", "achternaam": "Koning", "voorletters": "S.R.", "voornaam": "Saskia", "geslacht": "v", "stad": "Muiderberg", "partij_naam": "Forum voor Democratie", "tweede_poging": false, "vorige_partij": "", "vorige_woonplaats": "", "links": []}, "Hemmie Kerklingh": {"lijstnummer": 26, "kieskringen": ["Bonaire"], "naam": "Hemmie Kerklingh", "achternaam": "Kerklingh", "voorletters": "H.K.", "voornaam": "Hemmie", "geslacht": "m", "stad": "Diemen", "partij_naam": "Forum voor Democratie", "tweede_poging": false, "vorige_partij": "", "vorige_woonplaats": "", "links": []}, "Hendrikus Velzing": {"lijstnummer": 27, "kieskringen": ["Bonaire"], "naam": "Hendrikus Velzing", "achternaam": "Velzing", "voorletters": "H.", "voornaam": "Hendrikus", "geslacht": "m", "stad": "Klazienaveen", "partij_naam": "Forum voor Democratie", "tweede_poging": false, "vorige_partij": "", "vorige_woonplaats": "", "links": []}, "Loek van Wely": {"lijstnummer": 28, "kieskringen": ["Bonaire"], "naam": "Loek van Wely", "achternaam": "van Wely", "voorletters": "L.F.A.M.", "voornaam": "Loek", "geslacht": "m", "stad": "Tilburg", "partij_naam": "Forum voor Democratie", "tweede_poging": false, "vorige_partij": "", "vorige_woonplaats": "", "links": []}, "Frank Ankersmit": {"lijstnummer": 29, "kieskringen": ["Bonaire"], "naam": "Frank Ankersmit", "achternaam": "Ankersmit", "voorletters": "F.R.", "voornaam": "Frank", "geslacht": "m", "stad": "Glimmen", "partij_naam": "Forum voor Democratie", "tweede_poging": false, "vorige_partij": "", "vorige_woonplaats": "", "links": []}, "Paul Cliteur": {"lijstnummer": 30, "kieskringen": ["Bonaire"], "naam": "Paul Cliteur", "achternaam": "Cliteur", "voorletters": "P.B.", "voornaam": "Paul", "geslacht": "m", "stad": "Amsterdam", "partij_naam": "Forum voor Democratie", "tweede_poging": false, "vorige_partij": "", "vorige_woonplaats": "", "links": []}}