{"Femke Merel Kooten-Arissen": {"lijstnummer": 1, "kieskringen": ["Groningen", "Leeuwarden", "Assen", "Zwolle", "Lelystad", "Nijmegen", "Arnhem", "Utrecht", "Amsterdam", "Haarlem", "Den Helder", "'s-Gravenhage", "Rotterdam", "Dordrecht", "Leiden", "Middelburg", "Tilburg", "'s-Hertogenbosch", "Maastricht"], "naam": "Femke Merel Kooten-Arissen", "achternaam": "Kooten-Arissen", "voorletters": "F.M.", "voornaam": "Femke Merel", "geslacht": "v", "stad": "Woerden", "partij_naam": "Splinter", "tweede_poging": false, "vorige_partij": "", "vorige_woonplaats": "", "links": [], "gemeente": "Woerden", "provincie": "Utrecht"}, "Marjan Schnetz": {"lijstnummer": 2, "kieskringen": ["Groningen", "Leeuwarden", "Assen", "Zwolle", "Lelystad", "Nijmegen", "Arnhem", "Utrecht", "Amsterdam", "Haarlem", "Den Helder", "'s-Gravenhage", "Rotterdam", "Dordrecht", "Leiden", "Middelburg", "Tilburg", "'s-Hertogenbosch", "Maastricht"], "naam": "Marjan Schnetz", "achternaam": "Schnetz", "voorletters": "M.", "voornaam": "Marjan", "geslacht": "v", "stad": "'s-Gravenhage", "partij_naam": "Splinter", "tweede_poging": false, "vorige_partij": "", "vorige_woonplaats": "", "links": [], "gemeente": "Den Haag", "provincie": "Zuid-Holland"}, "Fabian Hal": {"lijstnummer": 3, "kieskringen": ["Groningen", "Leeuwarden", "Assen", "Zwolle", "Lelystad", "Nijmegen", "Arnhem", "Utrecht", "Amsterdam", "Haarlem", "Den Helder", "'s-Gravenhage", "Rotterdam", "Dordrecht", "Leiden", "Middelburg", "Tilburg", "'s-Hertogenbosch", "Maastricht"], "naam": "Fabian Hal", "achternaam": "Hal", "voorletters": "F.", "voornaam": "Fabian", "geslacht": "m", "stad": "Amsterdam", "partij_naam": "Splinter", "tweede_poging": false, "vorige_partij": "", "vorige_woonplaats": "", "links": [], "gemeente": "Amsterdam", "provincie": "Noord-Holland"}, "Giovanni Angiolini Trapanese": {"lijstnummer": 4, "kieskringen": ["Groningen", "Leeuwarden", "Assen", "Zwolle", "Lelystad", "Nijmegen", "Arnhem", "Utrecht", "Amsterdam", "Haarlem", "Den Helder", "'s-Gravenhage", "Rotterdam", "Dordrecht", "Leiden", "Middelburg", "Tilburg", "'s-Hertogenbosch", "Maastricht"], "naam": "Giovanni Angiolini Trapanese", "achternaam": "Angiolini Trapanese", "voorletters": "G.C.", "voornaam": "Giovanni", "geslacht": "m", "stad": "Voorburg", "partij_naam": "Splinter", "tweede_poging": false, "vorige_partij": "", "vorige_woonplaats": "", "links": [], "gemeente": "Leidschendam-Voorburg", "provincie": "Zuid-Holland"}, "Ingrid Keyser": {"lijstnummer": 5, "kieskringen": ["Groningen", "Leeuwarden", "Assen", "Zwolle", "Lelystad", "Nijmegen", "Arnhem", "Utrecht", "Amsterdam", "Haarlem", "Den Helder", "'s-Gravenhage", "Rotterdam", "Dordrecht", "Leiden", "Middelburg", "Tilburg", "'s-Hertogenbosch", "Maastricht"], "naam": "Ingrid Keyser", "achternaam": "Keyser", "voorletters": "I.", "voornaam": "Ingrid", "geslacht": "v", "stad": "Amsterdam", "partij_naam": "Splinter", "tweede_poging": false, "vorige_partij": "", "vorige_woonplaats": "", "links": [], "gemeente": "Amsterdam", "provincie": "Noord-Holland"}, "Shad Raouf": {"lijstnummer": 6, "kieskringen": ["Groningen", "Leeuwarden", "Assen", "Zwolle", "Lelystad", "Nijmegen", "Arnhem", "Utrecht", "Amsterdam", "Haarlem", "Den Helder", "'s-Gravenhage", "Rotterdam", "Dordrecht", "Leiden", "Middelburg", "Tilburg", "'s-Hertogenbosch", "Maastricht"], "naam": "Shad Raouf", "achternaam": "Raouf", "voorletters": "S.A.A.", "voornaam": "Shad", "geslacht": "m", "stad": "Nijmegen", "partij_naam": "Splinter", "tweede_poging": false, "vorige_partij": "", "vorige_woonplaats": "", "links": [], "gemeente": "Nijmegen", "provincie": "Gelderland"}, "Marise Schot": {"lijstnummer": 7, "kieskringen": ["Groningen", "Leeuwarden", "Assen", "Zwolle", "Lelystad", "Nijmegen", "Arnhem", "Utrecht", "Amsterdam", "Haarlem", "Den Helder", "'s-Gravenhage", "Rotterdam", "Dordrecht", "Leiden", "Middelburg", "Tilburg", "'s-Hertogenbosch", "Maastricht"], "naam": "Marise Schot", "achternaam": "Schot", "voorletters": "M.", "voornaam": "Marise", "geslacht": "v", "stad": "Delft", "partij_naam": "Splinter", "tweede_poging": false, "vorige_partij": "", "vorige_woonplaats": "", "links": [], "gemeente": "Delft", "provincie": "Zuid-Holland"}, "Elisabeth Leeuwen": {"lijstnummer": 8, "kieskringen": ["Groningen", "Leeuwarden", "Assen", "Zwolle", "Lelystad", "Nijmegen", "Arnhem", "Utrecht", "Amsterdam", "Haarlem", "Den Helder", "'s-Gravenhage", "Rotterdam", "Dordrecht", "Leiden", "Middelburg", "Tilburg", "'s-Hertogenbosch", "Maastricht"], "naam": "Elisabeth Leeuwen", "achternaam": "Leeuwen", "voorletters": "E.M.", "voornaam": "Elisabeth", "geslacht": "v", "stad": "Amsterdam", "partij_naam": "Splinter", "tweede_poging": false, "vorige_partij": "", "vorige_woonplaats": "", "links": [], "gemeente": "Amsterdam", "provincie": "Noord-Holland"}, "Ren\u00e9 Jan Veldwijk": {"lijstnummer": 9, "kieskringen": ["Groningen", "Leeuwarden", "Assen", "Zwolle", "Lelystad", "Nijmegen", "Arnhem", "Utrecht", "Amsterdam", "Haarlem", "Den Helder", "'s-Gravenhage", "Rotterdam", "Dordrecht", "Leiden", "Middelburg", "Tilburg", "'s-Hertogenbosch", "Maastricht"], "naam": "Ren\u00e9 Jan Veldwijk", "achternaam": "Veldwijk", "voorletters": "R.J.", "voornaam": "Ren\u00e9 Jan", "geslacht": "m", "stad": "'s-Gravenhage", "partij_naam": "Splinter", "tweede_poging": false, "vorige_partij": "", "vorige_woonplaats": "", "links": [], "gemeente": "Den Haag", "provincie": "Zuid-Holland"}, "Magda \u0141uczycki": {"lijstnummer": 10, "kieskringen": ["Groningen", "Leeuwarden", "Assen", "Zwolle", "Lelystad", "Nijmegen", "Arnhem", "Utrecht", "Amsterdam", "Haarlem", "Den Helder", "'s-Gravenhage", "Rotterdam", "Dordrecht", "Leiden", "Middelburg", "Tilburg", "'s-Hertogenbosch", "Maastricht"], "naam": "Magda \u0141uczycki", "achternaam": "\u0141uczycki", "voorletters": "M.", "voornaam": "Magda", "geslacht": "v", "stad": "Woerden", "partij_naam": "Splinter", "tweede_poging": false, "vorige_partij": "", "vorige_woonplaats": "", "links": [], "gemeente": "Woerden", "provincie": "Utrecht"}, "Mauritius Wijffels": {"lijstnummer": 11, "kieskringen": ["Groningen", "Leeuwarden", "Assen", "Zwolle", "Lelystad", "Nijmegen", "Arnhem", "Utrecht", "Amsterdam", "Haarlem", "Den Helder", "'s-Gravenhage", "Rotterdam", "Dordrecht", "Leiden", "Middelburg", "Tilburg", "'s-Hertogenbosch", "Maastricht"], "naam": "Mauritius Wijffels", "achternaam": "Wijffels", "voorletters": "M.B.M.", "voornaam": "Mauritius", "geslacht": "m", "stad": "Amsterdam", "partij_naam": "Splinter", "tweede_poging": false, "vorige_partij": "", "vorige_woonplaats": "", "links": [], "gemeente": "Amsterdam", "provincie": "Noord-Holland"}, "Meiny Prins": {"lijstnummer": 12, "kieskringen": ["Groningen", "Leeuwarden", "Assen", "Zwolle", "Lelystad", "Nijmegen", "Arnhem", "Utrecht", "Amsterdam", "Haarlem", "Den Helder", "'s-Gravenhage", "Rotterdam", "Dordrecht", "Leiden", "Middelburg", "Tilburg", "'s-Hertogenbosch", "Maastricht"], "naam": "Meiny Prins", "achternaam": "Prins", "voorletters": "M.M.C.", "voornaam": "Meiny", "geslacht": "v", "stad": "Weggis (CH)", "partij_naam": "Splinter", "tweede_poging": false, "vorige_partij": "", "vorige_woonplaats": "", "links": [], "gemeente": "Overig", "provincie": "Overig"}}