{"Anna Zeven": {"lijstnummer": 1, "kieskringen": ["Assen", "Zwolle", "Nijmegen", "Arnhem", "Den Helder", "Rotterdam", "Dordrecht", "Leiden", "Middelburg", "Tilburg", "'s-Hertogenbosch", "Maastricht"], "naam": "Anna Zeven", "achternaam": "Zeven", "voorletters": "A.J.L.B.", "voornaam": "Anna", "geslacht": "v", "stad": "'s-Gravenhage", "partij_naam": "blanco lijst met als eerste kandidaat Zeven, A.J.L.B.", "tweede_poging": false, "vorige_partij": ""}, "Willem Engel": {"lijstnummer": 2, "kieskringen": ["Assen", "Zwolle", "Nijmegen", "Arnhem", "Den Helder", "Rotterdam", "Dordrecht", "Leiden", "Middelburg", "Tilburg", "'s-Hertogenbosch", "Maastricht"], "naam": "Willem Engel", "achternaam": "Engel", "voorletters": "W.C.", "voornaam": "Willem", "geslacht": "m", "stad": "Rotterdam", "partij_naam": "blanco lijst met als eerste kandidaat Zeven, A.J.L.B.", "tweede_poging": false, "vorige_partij": ""}, "Mordechai Krispijn": {"lijstnummer": 3, "kieskringen": ["Assen", "Zwolle", "Nijmegen", "Arnhem", "Den Helder", "Rotterdam", "Dordrecht", "Leiden", "Middelburg", "Tilburg", "'s-Hertogenbosch", "Maastricht"], "naam": "Mordechai Krispijn", "achternaam": "Krispijn", "voorletters": "M.", "voornaam": "Mordechai", "geslacht": "m", "stad": "'s-Gravenhage", "partij_naam": "blanco lijst met als eerste kandidaat Zeven, A.J.L.B.", "tweede_poging": false, "vorige_partij": ""}, "Koen Verhagen": {"lijstnummer": 4, "kieskringen": ["Assen", "Zwolle", "Nijmegen", "Arnhem", "Den Helder", "Rotterdam", "Dordrecht", "Leiden", "Middelburg", "Tilburg", "'s-Hertogenbosch", "Maastricht"], "naam": "Koen Verhagen", "achternaam": "Verhagen", "voorletters": "K.E.B.M.", "voornaam": "Koen", "geslacht": "m", "stad": "Hulst", "partij_naam": "blanco lijst met als eerste kandidaat Zeven, A.J.L.B.", "tweede_poging": false, "vorige_partij": ""}, "Theo Vos": {"lijstnummer": 5, "kieskringen": ["Assen", "Zwolle", "Nijmegen", "Arnhem", "Den Helder", "Rotterdam", "Dordrecht", "Leiden", "Middelburg", "Tilburg", "'s-Hertogenbosch", "Maastricht"], "naam": "Theo Vos", "achternaam": "Vos", "voorletters": "T.G.", "voornaam": "Theo", "geslacht": "m", "stad": "Laren", "partij_naam": "blanco lijst met als eerste kandidaat Zeven, A.J.L.B.", "tweede_poging": false, "vorige_partij": ""}, "Christian Kromme": {"lijstnummer": 6, "kieskringen": ["Assen", "Zwolle", "Nijmegen", "Arnhem", "Den Helder", "Rotterdam", "Dordrecht", "Leiden", "Middelburg", "Tilburg", "'s-Hertogenbosch", "Maastricht"], "naam": "Christian Kromme", "achternaam": "Kromme", "voorletters": "C.B.", "voornaam": "Christian", "geslacht": "m", "stad": "Elburg", "partij_naam": "blanco lijst met als eerste kandidaat Zeven, A.J.L.B.", "tweede_poging": false, "vorige_partij": ""}, "Paul Brenkman": {"lijstnummer": 7, "kieskringen": ["Assen", "Zwolle", "Nijmegen", "Arnhem", "Den Helder", "Rotterdam", "Dordrecht", "Leiden", "Middelburg", "Tilburg", "'s-Hertogenbosch", "Maastricht"], "naam": "Paul Brenkman", "achternaam": "Brenkman", "voorletters": "P.", "voornaam": "Paul", "geslacht": "m", "stad": "Schiedam", "partij_naam": "blanco lijst met als eerste kandidaat Zeven, A.J.L.B.", "tweede_poging": false, "vorige_partij": ""}, "Steven de Oude": {"lijstnummer": 8, "kieskringen": ["Assen", "Zwolle", "Nijmegen", "Arnhem", "Den Helder", "Rotterdam", "Dordrecht", "Leiden", "Middelburg", "Tilburg", "'s-Hertogenbosch", "Maastricht"], "naam": "Steven de Oude", "achternaam": "de Oude", "voorletters": "S.N.", "voornaam": "Steven", "geslacht": "m", "stad": "Alphen aan den Rijn", "partij_naam": "blanco lijst met als eerste kandidaat Zeven, A.J.L.B.", "tweede_poging": false, "vorige_partij": ""}, "Ferenc Honkoop": {"lijstnummer": 9, "kieskringen": ["Assen", "Zwolle", "Nijmegen", "Arnhem", "Den Helder", "Rotterdam", "Dordrecht", "Leiden", "Middelburg", "Tilburg", "'s-Hertogenbosch", "Maastricht"], "naam": "Ferenc Honkoop", "achternaam": "Honkoop", "voorletters": "F.S.", "voornaam": "Ferenc", "geslacht": "m", "stad": "Kaatsheuvel", "partij_naam": "blanco lijst met als eerste kandidaat Zeven, A.J.L.B.", "tweede_poging": false, "vorige_partij": ""}, "Felix Tangelder": {"lijstnummer": 10, "kieskringen": ["Assen", "Zwolle", "Nijmegen", "Arnhem", "Den Helder", "Rotterdam", "Dordrecht", "Leiden", "Middelburg", "Tilburg", "'s-Hertogenbosch", "Maastricht"], "naam": "Felix Tangelder", "achternaam": "Tangelder", "voorletters": "F.T.", "voornaam": "Felix", "geslacht": "m", "stad": "Arnhem", "partij_naam": "blanco lijst met als eerste kandidaat Zeven, A.J.L.B.", "tweede_poging": false, "vorige_partij": ""}, "Omar Tegel": {"lijstnummer": 11, "kieskringen": ["Assen", "Zwolle", "Nijmegen", "Arnhem", "Den Helder", "Rotterdam", "Dordrecht", "Leiden", "Middelburg", "Tilburg", "'s-Hertogenbosch", "Maastricht"], "naam": "Omar Tegel", "achternaam": "Tegel", "voorletters": "O.", "voornaam": "Omar", "geslacht": "m", "stad": "Heiloo", "partij_naam": "blanco lijst met als eerste kandidaat Zeven, A.J.L.B.", "tweede_poging": false, "vorige_partij": ""}, "Simcha de Haan": {"lijstnummer": 12, "kieskringen": ["Assen", "Zwolle", "Nijmegen", "Arnhem", "Den Helder", "Rotterdam", "Dordrecht", "Leiden", "Middelburg", "Tilburg", "'s-Hertogenbosch", "Maastricht"], "naam": "Simcha de Haan", "achternaam": "de Haan", "voorletters": "S.", "voornaam": "Simcha", "geslacht": "v", "stad": "Amsterdam", "partij_naam": "blanco lijst met als eerste kandidaat Zeven, A.J.L.B.", "tweede_poging": false, "vorige_partij": ""}, "Inez van Baarsen": {"lijstnummer": 13, "kieskringen": ["Assen", "Zwolle", "Nijmegen", "Arnhem", "Den Helder", "Rotterdam", "Dordrecht", "Leiden", "Middelburg", "Tilburg", "'s-Hertogenbosch", "Maastricht"], "naam": "Inez van Baarsen", "achternaam": "van Baarsen", "voorletters": "I.T.", "voornaam": "Inez", "geslacht": "v", "stad": "Zutphen", "partij_naam": "blanco lijst met als eerste kandidaat Zeven, A.J.L.B.", "tweede_poging": false, "vorige_partij": ""}, "Melissa de Ruijter": {"lijstnummer": 14, "kieskringen": ["Assen", "Zwolle", "Nijmegen", "Arnhem", "Den Helder", "Rotterdam", "Dordrecht", "Leiden", "Middelburg", "Tilburg", "'s-Hertogenbosch", "Maastricht"], "naam": "Melissa de Ruijter", "achternaam": "de Ruijter", "voorletters": "M.D.I.", "voornaam": "Melissa", "geslacht": "v", "stad": "Wognum", "partij_naam": "blanco lijst met als eerste kandidaat Zeven, A.J.L.B.", "tweede_poging": false, "vorige_partij": ""}, "Ramona Kwestro": {"lijstnummer": 15, "kieskringen": ["Assen", "Zwolle", "Nijmegen", "Arnhem", "Den Helder", "Rotterdam", "Dordrecht", "Leiden", "Middelburg", "Tilburg", "'s-Hertogenbosch", "Maastricht"], "naam": "Ramona Kwestro", "achternaam": "Kwestro", "voorletters": "R.", "voornaam": "Ramona", "geslacht": "v", "stad": "Leiden", "partij_naam": "blanco lijst met als eerste kandidaat Zeven, A.J.L.B.", "tweede_poging": false, "vorige_partij": ""}, "Lisa van Archipel": {"lijstnummer": 16, "kieskringen": ["Assen", "Zwolle", "Nijmegen", "Arnhem", "Den Helder", "Rotterdam", "Dordrecht", "Leiden", "Middelburg", "Tilburg", "'s-Hertogenbosch", "Maastricht"], "naam": "Lisa van Archipel", "achternaam": "van Archipel", "voorletters": "L.M.E.", "voornaam": "Lisa", "geslacht": "v", "stad": "'s-Gravenhage", "partij_naam": "blanco lijst met als eerste kandidaat Zeven, A.J.L.B.", "tweede_poging": false, "vorige_partij": ""}, "Rick Artz": {"lijstnummer": 17, "kieskringen": ["Assen", "Zwolle", "Nijmegen", "Arnhem", "Den Helder", "Rotterdam", "Dordrecht", "Leiden", "Middelburg", "Tilburg", "'s-Hertogenbosch", "Maastricht"], "naam": "Rick Artz", "achternaam": "Artz", "voorletters": "H.A.M.", "voornaam": "Rick", "geslacht": "m", "stad": "Wijk en Aalburg", "partij_naam": "blanco lijst met als eerste kandidaat Zeven, A.J.L.B.", "tweede_poging": false, "vorige_partij": ""}, "Edward Kleinjan": {"lijstnummer": 18, "kieskringen": ["Assen", "Zwolle", "Nijmegen", "Arnhem", "Den Helder", "Rotterdam", "Dordrecht", "Leiden", "Middelburg", "Tilburg", "'s-Hertogenbosch", "Maastricht"], "naam": "Edward Kleinjan", "achternaam": "Kleinjan", "voorletters": "E.A.", "voornaam": "Edward", "geslacht": "m", "stad": "Huizen", "partij_naam": "blanco lijst met als eerste kandidaat Zeven, A.J.L.B.", "tweede_poging": false, "vorige_partij": ""}, "Wilko Huiden": {"lijstnummer": 19, "kieskringen": ["Assen", "Zwolle", "Nijmegen", "Arnhem", "Den Helder", "Rotterdam", "Dordrecht", "Leiden", "Middelburg", "Tilburg", "'s-Hertogenbosch", "Maastricht"], "naam": "Wilko Huiden", "achternaam": "Huiden", "voorletters": "W.R.J.", "voornaam": "Wilko", "geslacht": "m", "stad": "Zoetermeer", "partij_naam": "blanco lijst met als eerste kandidaat Zeven, A.J.L.B.", "tweede_poging": false, "vorige_partij": ""}, "Ab Gietelink": {"lijstnummer": 20, "kieskringen": ["Assen", "Zwolle", "Nijmegen", "Arnhem", "Den Helder", "Rotterdam", "Dordrecht", "Leiden", "Middelburg", "Tilburg", "'s-Hertogenbosch", "Maastricht"], "naam": "Ab Gietelink", "achternaam": "Gietelink", "voorletters": "A.C.", "voornaam": "Ab", "geslacht": "m", "stad": "Amsterdam", "partij_naam": "blanco lijst met als eerste kandidaat Zeven, A.J.L.B.", "tweede_poging": false, "vorige_partij": ""}, "Kees van der Pijl": {"lijstnummer": 21, "kieskringen": ["Assen", "Zwolle", "Nijmegen", "Arnhem", "Den Helder", "Rotterdam", "Dordrecht", "Leiden", "Middelburg", "Tilburg", "'s-Hertogenbosch", "Maastricht"], "naam": "Kees van der Pijl", "achternaam": "van der Pijl", "voorletters": "K.", "voornaam": "Kees", "geslacht": "m", "stad": "Amsterdam", "partij_naam": "blanco lijst met als eerste kandidaat Zeven, A.J.L.B.", "tweede_poging": false, "vorige_partij": ""}}