{"Lilianne Ploumen": {"lijstnummer": 1, "kieskringen": ["Groningen", "Leeuwarden", "Assen", "Zwolle", "Lelystad", "Nijmegen", "Arnhem", "Utrecht", "Amsterdam", "Haarlem", "Den Helder", "'s-Gravenhage", "Rotterdam", "Dordrecht", "Leiden", "Middelburg", "Tilburg", "'s-Hertogenbosch", "Maastricht", "Bonaire"], "naam": "Lilianne Ploumen", "achternaam": "Ploumen", "voorletters": "E.M.J.", "voornaam": "Lilianne", "geslacht": "v", "stad": "Amsterdam", "partij_naam": "Partij van de Arbeid (P.v.d.A.)", "tweede_poging": true, "vorige_partij": ""}, "Khadija Arib": {"lijstnummer": 2, "kieskringen": ["Groningen", "Leeuwarden", "Assen", "Zwolle", "Lelystad", "Nijmegen", "Arnhem", "Utrecht", "Amsterdam", "Haarlem", "Den Helder", "'s-Gravenhage", "Rotterdam", "Dordrecht", "Leiden", "Middelburg", "Tilburg", "'s-Hertogenbosch", "Maastricht", "Bonaire"], "naam": "Khadija Arib", "achternaam": "Arib", "voorletters": "K.", "voornaam": "Khadija", "geslacht": "v", "stad": "Amsterdam", "partij_naam": "Partij van de Arbeid (P.v.d.A.)", "tweede_poging": true, "vorige_partij": ""}, "Henk Nijboer": {"lijstnummer": 3, "kieskringen": ["Groningen", "Leeuwarden", "Assen", "Zwolle", "Lelystad", "Nijmegen", "Arnhem", "Utrecht", "Amsterdam", "Haarlem", "Den Helder", "'s-Gravenhage", "Rotterdam", "Dordrecht", "Leiden", "Middelburg", "Tilburg", "'s-Hertogenbosch", "Maastricht", "Bonaire"], "naam": "Henk Nijboer", "achternaam": "Nijboer", "voorletters": "H.", "voornaam": "Henk", "geslacht": "m", "stad": "Groningen", "partij_naam": "Partij van de Arbeid (P.v.d.A.)", "tweede_poging": true, "vorige_partij": ""}, "Attje Kuiken": {"lijstnummer": 4, "kieskringen": ["Groningen", "Leeuwarden", "Assen", "Zwolle", "Lelystad", "Nijmegen", "Arnhem", "Utrecht", "Amsterdam", "Haarlem", "Den Helder", "'s-Gravenhage", "Rotterdam", "Dordrecht", "Leiden", "Middelburg", "Tilburg", "'s-Hertogenbosch", "Maastricht", "Bonaire"], "naam": "Attje Kuiken", "achternaam": "Kuiken", "voorletters": "A.H.", "voornaam": "Attje", "geslacht": "v", "stad": "Breda", "partij_naam": "Partij van de Arbeid (P.v.d.A.)", "tweede_poging": true, "vorige_partij": ""}, "Kati Piri": {"lijstnummer": 5, "kieskringen": ["Groningen", "Leeuwarden", "Assen", "Zwolle", "Lelystad", "Nijmegen", "Arnhem", "Utrecht", "Amsterdam", "Haarlem", "Den Helder", "'s-Gravenhage", "Rotterdam", "Dordrecht", "Leiden", "Middelburg", "Tilburg", "'s-Hertogenbosch", "Maastricht", "Bonaire"], "naam": "Kati Piri", "achternaam": "Piri", "voorletters": "K.P.", "voornaam": "Kati", "geslacht": "v", "stad": "'s-Gravenhage", "partij_naam": "Partij van de Arbeid (P.v.d.A.)", "tweede_poging": true, "vorige_partij": ""}, "Joris Thijssen": {"lijstnummer": 6, "kieskringen": ["Groningen", "Leeuwarden", "Assen", "Zwolle", "Lelystad", "Nijmegen", "Arnhem", "Utrecht", "Amsterdam", "Haarlem", "Den Helder", "'s-Gravenhage", "Rotterdam", "Dordrecht", "Leiden", "Middelburg", "Tilburg", "'s-Hertogenbosch", "Maastricht", "Bonaire"], "naam": "Joris Thijssen", "achternaam": "Thijssen", "voorletters": "J.", "voornaam": "Joris", "geslacht": "m", "stad": "Muiderberg", "partij_naam": "Partij van de Arbeid (P.v.d.A.)", "tweede_poging": false, "vorige_partij": ""}, "Barbara Kathmann": {"lijstnummer": 7, "kieskringen": ["Groningen", "Leeuwarden", "Assen", "Zwolle", "Lelystad", "Nijmegen", "Arnhem", "Utrecht", "Amsterdam", "Haarlem", "Den Helder", "'s-Gravenhage", "Rotterdam", "Dordrecht", "Leiden", "Middelburg", "Tilburg", "'s-Hertogenbosch", "Maastricht", "Bonaire"], "naam": "Barbara Kathmann", "achternaam": "Kathmann", "voorletters": "B.C.", "voornaam": "Barbara", "geslacht": "v", "stad": "Rotterdam", "partij_naam": "Partij van de Arbeid (P.v.d.A.)", "tweede_poging": false, "vorige_partij": ""}, "Gijs van Dijk": {"lijstnummer": 8, "kieskringen": ["Groningen", "Leeuwarden", "Assen", "Zwolle", "Lelystad", "Nijmegen", "Arnhem", "Utrecht", "Amsterdam", "Haarlem", "Den Helder", "'s-Gravenhage", "Rotterdam", "Dordrecht", "Leiden", "Middelburg", "Tilburg", "'s-Hertogenbosch", "Maastricht", "Bonaire"], "naam": "Gijs van Dijk", "achternaam": "van Dijk", "voorletters": "G.J.", "voornaam": "Gijs", "geslacht": "m", "stad": "Den Burg", "partij_naam": "Partij van de Arbeid (P.v.d.A.)", "tweede_poging": true, "vorige_partij": ""}, "Habtamu de Hoop": {"lijstnummer": 9, "kieskringen": ["Groningen", "Leeuwarden", "Assen", "Zwolle", "Lelystad", "Nijmegen", "Arnhem", "Utrecht", "Amsterdam", "Haarlem", "Den Helder", "'s-Gravenhage", "Rotterdam", "Dordrecht", "Leiden", "Middelburg", "Tilburg", "'s-Hertogenbosch", "Maastricht", "Bonaire"], "naam": "Habtamu de Hoop", "achternaam": "de Hoop", "voorletters": "H.E.", "voornaam": "Habtamu", "geslacht": "m", "stad": "Easterein", "partij_naam": "Partij van de Arbeid (P.v.d.A.)", "tweede_poging": false, "vorige_partij": ""}, "Songül Mutluer": {"lijstnummer": 10, "kieskringen": ["Groningen", "Leeuwarden", "Assen", "Zwolle", "Lelystad", "Nijmegen", "Arnhem", "Utrecht", "Amsterdam", "Haarlem", "Den Helder", "'s-Gravenhage", "Rotterdam", "Dordrecht", "Leiden", "Middelburg", "Tilburg", "'s-Hertogenbosch", "Maastricht", "Bonaire"], "naam": "Songül Mutluer", "achternaam": "Mutluer", "voorletters": "S.", "voornaam": "Songül", "geslacht": "v", "stad": "Zaandam", "partij_naam": "Partij van de Arbeid (P.v.d.A.)", "tweede_poging": false, "vorige_partij": ""}, "Mohammed Mohandis": {"lijstnummer": 11, "kieskringen": ["Groningen", "Leeuwarden", "Assen", "Zwolle", "Lelystad", "Nijmegen", "Arnhem", "Utrecht", "Amsterdam", "Haarlem", "Den Helder", "'s-Gravenhage", "Rotterdam", "Dordrecht", "Leiden", "Middelburg", "Tilburg", "'s-Hertogenbosch", "Maastricht", "Bonaire"], "naam": "Mohammed Mohandis", "achternaam": "Mohandis", "voorletters": "M.", "voornaam": "Mohammed", "geslacht": "m", "stad": "Gouda", "partij_naam": "Partij van de Arbeid (P.v.d.A.)", "tweede_poging": true, "vorige_partij": ""}, "Kirsten van den Hul": {"lijstnummer": 12, "kieskringen": ["Groningen", "Leeuwarden", "Assen", "Zwolle", "Lelystad", "Nijmegen", "Arnhem", "Utrecht", "Amsterdam", "Haarlem", "Den Helder", "'s-Gravenhage", "Rotterdam", "Dordrecht", "Leiden", "Middelburg", "Tilburg", "'s-Hertogenbosch", "Maastricht", "Bonaire"], "naam": "Kirsten van den Hul", "achternaam": "van den Hul", "voorletters": "K.A.E.", "voornaam": "Kirsten", "geslacht": "v", "stad": "'s-Gravenhage", "partij_naam": "Partij van de Arbeid (P.v.d.A.)", "tweede_poging": true, "vorige_partij": ""}, "Julian Bushoff": {"lijstnummer": 13, "kieskringen": ["Groningen", "Leeuwarden", "Assen", "Zwolle", "Lelystad", "Nijmegen", "Arnhem", "Utrecht", "Amsterdam", "Haarlem", "Den Helder", "'s-Gravenhage", "Rotterdam", "Dordrecht", "Leiden", "Middelburg", "Tilburg", "'s-Hertogenbosch", "Maastricht", "Bonaire"], "naam": "Julian Bushoff", "achternaam": "Bushoff", "voorletters": "T.J.", "voornaam": "Julian", "geslacht": "m", "stad": "Groningen", "partij_naam": "Partij van de Arbeid (P.v.d.A.)", "tweede_poging": false, "vorige_partij": ""}, "Kavish Bisseswar": {"lijstnummer": 14, "kieskringen": ["Groningen", "Leeuwarden", "Assen", "Zwolle", "Lelystad", "Nijmegen", "Arnhem", "Utrecht", "Amsterdam", "Haarlem", "Den Helder", "'s-Gravenhage", "Rotterdam", "Dordrecht", "Leiden", "Middelburg", "Tilburg", "'s-Hertogenbosch", "Maastricht", "Bonaire"], "naam": "Kavish Bisseswar", "achternaam": "Bisseswar", "voorletters": "K.J.R.", "voornaam": "Kavish", "geslacht": "m", "stad": "Beijing (CN)", "partij_naam": "Partij van de Arbeid (P.v.d.A.)", "tweede_poging": false, "vorige_partij": ""}, "Charlotte Brand": {"lijstnummer": 15, "kieskringen": ["Groningen", "Leeuwarden", "Assen", "Zwolle", "Lelystad", "Nijmegen", "Arnhem", "Utrecht", "Amsterdam", "Haarlem", "Den Helder", "'s-Gravenhage", "Rotterdam", "Dordrecht", "Leiden", "Middelburg", "Tilburg", "'s-Hertogenbosch", "Maastricht", "Bonaire"], "naam": "Charlotte Brand", "achternaam": "Brand", "voorletters": "C.J.M.", "voornaam": "Charlotte", "geslacht": "v", "stad": "Nijmegen", "partij_naam": "Partij van de Arbeid (P.v.d.A.)", "tweede_poging": false, "vorige_partij": ""}, "Sofyan Mbarki": {"lijstnummer": 16, "kieskringen": ["Groningen", "Leeuwarden", "Assen", "Zwolle", "Lelystad", "Nijmegen", "Arnhem", "Utrecht", "Amsterdam", "Haarlem", "Den Helder", "'s-Gravenhage", "Rotterdam", "Dordrecht", "Leiden", "Middelburg", "Tilburg", "'s-Hertogenbosch", "Maastricht", "Bonaire"], "naam": "Sofyan Mbarki", "achternaam": "Mbarki", "voorletters": "S.", "voornaam": "Sofyan", "geslacht": "m", "stad": "Amsterdam", "partij_naam": "Partij van de Arbeid (P.v.d.A.)", "tweede_poging": false, "vorige_partij": ""}, "Mikal Tseggai": {"lijstnummer": 17, "kieskringen": ["Groningen", "Leeuwarden", "Assen", "Zwolle", "Lelystad", "Nijmegen", "Arnhem", "Utrecht", "Amsterdam", "Haarlem", "Den Helder", "'s-Gravenhage", "Rotterdam", "Dordrecht", "Leiden", "Middelburg", "Tilburg", "'s-Hertogenbosch", "Maastricht", "Bonaire"], "naam": "Mikal Tseggai", "achternaam": "Tseggai", "voorletters": "M.", "voornaam": "Mikal", "geslacht": "v", "stad": "'s-Gravenhage", "partij_naam": "Partij van de Arbeid (P.v.d.A.)", "tweede_poging": false, "vorige_partij": ""}, "Bart van Bruggen": {"lijstnummer": 18, "kieskringen": ["Groningen", "Leeuwarden", "Assen", "Zwolle", "Lelystad", "Nijmegen", "Arnhem", "Utrecht", "Amsterdam", "Haarlem", "Den Helder", "'s-Gravenhage", "Rotterdam", "Dordrecht", "Leiden", "Middelburg", "Tilburg", "'s-Hertogenbosch", "Maastricht", "Bonaire"], "naam": "Bart van Bruggen", "achternaam": "van Bruggen", "voorletters": "B.M.", "voornaam": "Bart", "geslacht": "m", "stad": "Utrecht", "partij_naam": "Partij van de Arbeid (P.v.d.A.)", "tweede_poging": false, "vorige_partij": ""}, "Christa Oosterbaan": {"lijstnummer": 19, "kieskringen": ["Groningen", "Leeuwarden", "Assen", "Zwolle", "Lelystad", "Nijmegen", "Arnhem", "Utrecht", "Amsterdam", "Haarlem", "Den Helder", "'s-Gravenhage", "Rotterdam", "Dordrecht", "Leiden", "Middelburg", "Tilburg", "'s-Hertogenbosch", "Maastricht", "Bonaire"], "naam": "Christa Oosterbaan", "achternaam": "Oosterbaan", "voorletters": "C.", "voornaam": "Christa", "geslacht": "v", "stad": "West-Terschelling", "partij_naam": "Partij van de Arbeid (P.v.d.A.)", "tweede_poging": true, "vorige_partij": ""}, "Barbara Oomen": {"lijstnummer": 20, "kieskringen": ["Groningen", "Leeuwarden", "Assen", "Zwolle", "Lelystad", "Nijmegen", "Arnhem", "Utrecht", "Amsterdam", "Haarlem", "Den Helder", "'s-Gravenhage", "Rotterdam", "Dordrecht", "Leiden", "Middelburg", "Tilburg", "'s-Hertogenbosch", "Maastricht", "Bonaire"], "naam": "Barbara Oomen", "achternaam": "Oomen", "voorletters": "B.M.", "voornaam": "Barbara", "geslacht": "v", "stad": "Middelburg", "partij_naam": "Partij van de Arbeid (P.v.d.A.)", "tweede_poging": false, "vorige_partij": ""}, "Inge Oosting": {"lijstnummer": 21, "kieskringen": ["Groningen", "Leeuwarden", "Assen", "Zwolle", "Lelystad", "Nijmegen", "Arnhem", "Utrecht", "Amsterdam", "Haarlem", "Den Helder", "'s-Gravenhage", "Rotterdam", "Dordrecht", "Leiden", "Middelburg", "Tilburg", "'s-Hertogenbosch", "Maastricht", "Bonaire"], "naam": "Inge Oosting", "achternaam": "Oosting", "voorletters": "I.", "voornaam": "Inge", "geslacht": "v", "stad": "Elim", "partij_naam": "Partij van de Arbeid (P.v.d.A.)", "tweede_poging": false, "vorige_partij": ""}, "Jasper Kuntzelaers": {"lijstnummer": 22, "kieskringen": ["Groningen", "Leeuwarden", "Assen", "Zwolle", "Lelystad", "Nijmegen", "Arnhem", "Utrecht", "Amsterdam", "Haarlem", "Den Helder", "'s-Gravenhage", "Rotterdam", "Dordrecht", "Leiden", "Middelburg", "Tilburg", "'s-Hertogenbosch", "Maastricht", "Bonaire"], "naam": "Jasper Kuntzelaers", "achternaam": "Kuntzelaers", "voorletters": "J.J.M.", "voornaam": "Jasper", "geslacht": "m", "stad": "Venlo", "partij_naam": "Partij van de Arbeid (P.v.d.A.)", "tweede_poging": false, "vorige_partij": ""}, "Mirthe Biemans": {"lijstnummer": 23, "kieskringen": ["Groningen", "Leeuwarden", "Assen", "Zwolle", "Lelystad", "Nijmegen", "Arnhem", "Utrecht", "Amsterdam", "Haarlem", "Den Helder", "'s-Gravenhage", "Rotterdam", "Dordrecht", "Leiden", "Middelburg", "Tilburg", "'s-Hertogenbosch", "Maastricht", "Bonaire"], "naam": "Mirthe Biemans", "achternaam": "Biemans", "voorletters": "M.S.", "voornaam": "Mirthe", "geslacht": "v", "stad": "Utrecht", "partij_naam": "Partij van de Arbeid (P.v.d.A.)", "tweede_poging": true, "vorige_partij": ""}, "Matthijs van Neerbos": {"lijstnummer": 24, "kieskringen": ["Groningen", "Leeuwarden", "Assen", "Zwolle", "Lelystad", "Nijmegen", "Arnhem", "Utrecht", "Amsterdam", "Haarlem", "Den Helder", "'s-Gravenhage", "Rotterdam", "Dordrecht", "Leiden", "Middelburg", "Tilburg", "'s-Hertogenbosch", "Maastricht", "Bonaire"], "naam": "Matthijs van Neerbos", "achternaam": "van Neerbos", "voorletters": "M.", "voornaam": "Matthijs", "geslacht": "m", "stad": "Rotterdam", "partij_naam": "Partij van de Arbeid (P.v.d.A.)", "tweede_poging": false, "vorige_partij": ""}, "Alptekin Akdogan": {"lijstnummer": 25, "kieskringen": ["Groningen", "Leeuwarden", "Assen", "Zwolle", "Lelystad", "Nijmegen", "Arnhem", "Utrecht", "Amsterdam", "Haarlem", "Den Helder", "'s-Gravenhage", "Rotterdam", "Dordrecht", "Leiden", "Middelburg", "Tilburg", "'s-Hertogenbosch", "Maastricht", "Bonaire"], "naam": "Alptekin Akdogan", "achternaam": "Akdogan", "voorletters": "A.", "voornaam": "Alptekin", "geslacht": "m", "stad": "Houten", "partij_naam": "Partij van de Arbeid (P.v.d.A.)", "tweede_poging": false, "vorige_partij": ""}, "Attiya Gamri": {"lijstnummer": 26, "kieskringen": ["Groningen", "Leeuwarden", "Assen", "Zwolle", "Lelystad", "Nijmegen", "Arnhem", "Utrecht", "Amsterdam", "Haarlem", "Den Helder", "'s-Gravenhage", "Rotterdam", "Dordrecht", "Leiden", "Middelburg", "Tilburg", "'s-Hertogenbosch", "Maastricht", "Bonaire"], "naam": "Attiya Gamri", "achternaam": "Gamri", "voorletters": "A.", "voornaam": "Attiya", "geslacht": "v", "stad": "Overveen", "partij_naam": "Partij van de Arbeid (P.v.d.A.)", "tweede_poging": false, "vorige_partij": ""}, "Iris Vrolijks": {"lijstnummer": 27, "kieskringen": ["Groningen", "Leeuwarden", "Assen", "Zwolle", "Lelystad", "Nijmegen", "Arnhem", "Utrecht", "Amsterdam", "Haarlem", "Den Helder", "'s-Gravenhage", "Rotterdam", "Dordrecht", "Leiden", "Middelburg", "Tilburg", "'s-Hertogenbosch", "Maastricht", "Bonaire"], "naam": "Iris Vrolijks", "achternaam": "Vrolijks", "voorletters": "I.L.", "voornaam": "Iris", "geslacht": "v", "stad": "Maassluis", "partij_naam": "Partij van de Arbeid (P.v.d.A.)", "tweede_poging": false, "vorige_partij": ""}, "Abassin Nessar": {"lijstnummer": 28, "kieskringen": ["Groningen", "Leeuwarden", "Assen", "Zwolle", "Lelystad", "Nijmegen", "Arnhem", "Utrecht", "Amsterdam", "Haarlem", "Den Helder", "'s-Gravenhage", "Rotterdam", "Dordrecht", "Leiden", "Middelburg", "Tilburg", "'s-Hertogenbosch", "Maastricht", "Bonaire"], "naam": "Abassin Nessar", "achternaam": "Nessar", "voorletters": "A.", "voornaam": "Abassin", "geslacht": "m", "stad": "Almere", "partij_naam": "Partij van de Arbeid (P.v.d.A.)", "tweede_poging": false, "vorige_partij": ""}, "Maarten van den Bos": {"lijstnummer": 29, "kieskringen": ["Groningen", "Leeuwarden", "Assen", "Zwolle", "Lelystad", "Nijmegen", "Arnhem", "Utrecht", "Amsterdam", "Haarlem", "Den Helder", "'s-Gravenhage", "Rotterdam", "Dordrecht", "Leiden", "Middelburg", "Tilburg", "'s-Hertogenbosch", "Maastricht", "Bonaire"], "naam": "Maarten van den Bos", "achternaam": "van den Bos", "voorletters": "M.J.A.", "voornaam": "Maarten", "geslacht": "m", "stad": "Bemmel", "partij_naam": "Partij van de Arbeid (P.v.d.A.)", "tweede_poging": false, "vorige_partij": ""}, "Fatihya Abdi": {"lijstnummer": 30, "kieskringen": ["Groningen", "Leeuwarden", "Assen", "Zwolle", "Lelystad", "Nijmegen", "Arnhem", "Utrecht", "Amsterdam", "Haarlem", "Den Helder", "'s-Gravenhage", "Rotterdam", "Dordrecht", "Leiden", "Middelburg", "Tilburg", "'s-Hertogenbosch", "Maastricht", "Bonaire"], "naam": "Fatihya Abdi", "achternaam": "Abdi", "voorletters": "F.", "voornaam": "Fatihya", "geslacht": "v", "stad": "Amsterdam", "partij_naam": "Partij van de Arbeid (P.v.d.A.)", "tweede_poging": false, "vorige_partij": ""}, "Stan Peters": {"lijstnummer": 31, "kieskringen": ["Groningen", "Leeuwarden", "Assen", "Zwolle", "Lelystad", "Nijmegen", "Arnhem", "Utrecht", "Amsterdam", "Haarlem", "Den Helder", "'s-Gravenhage", "Rotterdam", "Dordrecht", "Leiden", "Middelburg", "Tilburg", "'s-Hertogenbosch", "Maastricht", "Bonaire"], "naam": "Stan Peters", "achternaam": "Peters", "voorletters": "S.J.M.", "voornaam": "Stan", "geslacht": "m", "stad": "'s-Hertogenbosch", "partij_naam": "Partij van de Arbeid (P.v.d.A.)", "tweede_poging": false, "vorige_partij": ""}, "Lenna Vromans": {"lijstnummer": 32, "kieskringen": ["Groningen", "Leeuwarden", "Assen", "Zwolle", "Lelystad", "Nijmegen", "Arnhem", "Utrecht", "Amsterdam", "Haarlem", "Den Helder", "'s-Gravenhage", "Rotterdam", "Dordrecht", "Leiden", "Middelburg", "Tilburg", "'s-Hertogenbosch", "Maastricht", "Bonaire"], "naam": "Lenna Vromans", "achternaam": "Vromans", "voorletters": "L.J.M.", "voornaam": "Lenna", "geslacht": "v", "stad": "Heemstede", "partij_naam": "Partij van de Arbeid (P.v.d.A.)", "tweede_poging": false, "vorige_partij": ""}, "Rebekka Tselms": {"lijstnummer": 33, "kieskringen": ["Groningen", "Leeuwarden", "Assen", "Zwolle", "Lelystad", "Nijmegen", "Arnhem", "Utrecht", "Amsterdam", "Haarlem", "Den Helder", "'s-Gravenhage", "Rotterdam", "Dordrecht", "Leiden", "Middelburg", "Tilburg", "'s-Hertogenbosch", "Maastricht", "Bonaire"], "naam": "Rebekka Tselms", "achternaam": "Tselms", "voorletters": "R.V.", "voornaam": "Rebekka", "geslacht": "v", "stad": "Amsterdam", "partij_naam": "Partij van de Arbeid (P.v.d.A.)", "tweede_poging": false, "vorige_partij": ""}, "Marcelle Buitendam": {"lijstnummer": 34, "kieskringen": ["Groningen", "Leeuwarden", "Assen", "Zwolle", "Lelystad", "Nijmegen", "Arnhem", "Utrecht", "Amsterdam", "Haarlem", "Den Helder", "'s-Gravenhage", "Rotterdam", "Dordrecht", "Leiden", "Middelburg", "Tilburg", "'s-Hertogenbosch", "Maastricht", "Bonaire"], "naam": "Marcelle Buitendam", "achternaam": "Buitendam", "voorletters": "M.S.", "voornaam": "Marcelle", "geslacht": "v", "stad": "Vinkeveen", "partij_naam": "Partij van de Arbeid (P.v.d.A.)", "tweede_poging": false, "vorige_partij": ""}, "Loes Ypma": {"lijstnummer": 35, "kieskringen": ["Groningen", "Leeuwarden", "Assen", "Zwolle", "Lelystad", "Nijmegen", "Arnhem", "Utrecht", "Amsterdam", "Haarlem", "Den Helder", "'s-Gravenhage", "Rotterdam", "Dordrecht", "Leiden", "Middelburg", "Tilburg", "'s-Hertogenbosch", "Maastricht", "Bonaire"], "naam": "Loes Ypma", "achternaam": "Ypma", "voorletters": "L.", "voornaam": "Loes", "geslacht": "v", "stad": "Woerden", "partij_naam": "Partij van de Arbeid (P.v.d.A.)", "tweede_poging": true, "vorige_partij": ""}, "Jerzy Soetekouw": {"lijstnummer": 36, "kieskringen": ["Groningen", "Leeuwarden", "Assen", "Zwolle", "Lelystad", "Nijmegen", "Arnhem", "Utrecht", "Amsterdam", "Haarlem", "Den Helder", "'s-Gravenhage", "Rotterdam", "Dordrecht", "Leiden", "Middelburg", "Tilburg", "'s-Hertogenbosch", "Maastricht", "Bonaire"], "naam": "Jerzy Soetekouw", "achternaam": "Soetekouw", "voorletters": "J.A.", "voornaam": "Jerzy", "geslacht": "m", "stad": "Almere", "partij_naam": "Partij van de Arbeid (P.v.d.A.)", "tweede_poging": false, "vorige_partij": ""}, "Bas Bijlsma": {"lijstnummer": 37, "kieskringen": ["Groningen", "Leeuwarden", "Assen", "Zwolle", "Lelystad", "Nijmegen", "Arnhem", "Utrecht", "Amsterdam", "Haarlem", "Den Helder", "'s-Gravenhage", "Rotterdam", "Dordrecht", "Leiden", "Middelburg", "Tilburg", "'s-Hertogenbosch", "Maastricht", "Bonaire"], "naam": "Bas Bijlsma", "achternaam": "Bijlsma", "voorletters": "J.S.", "voornaam": "Bas", "geslacht": "m", "stad": "Amsterdam", "partij_naam": "Partij van de Arbeid (P.v.d.A.)", "tweede_poging": false, "vorige_partij": ""}, "Marieke van Duijn": {"lijstnummer": 38, "kieskringen": ["Groningen", "Leeuwarden", "Assen", "Zwolle", "Lelystad", "Nijmegen", "Arnhem", "Utrecht", "Amsterdam", "Haarlem", "Den Helder", "'s-Gravenhage", "Rotterdam", "Dordrecht", "Leiden", "Middelburg", "Tilburg", "'s-Hertogenbosch", "Maastricht", "Bonaire"], "naam": "Marieke van Duijn", "achternaam": "van Duijn", "voorletters": "E.M.", "voornaam": "Marieke", "geslacht": "v", "stad": "Haarlem", "partij_naam": "Partij van de Arbeid (P.v.d.A.)", "tweede_poging": false, "vorige_partij": ""}, "Joke de Kock": {"lijstnummer": 39, "kieskringen": ["Groningen", "Leeuwarden", "Assen", "Zwolle", "Lelystad", "Nijmegen", "Arnhem", "Utrecht", "Amsterdam", "Haarlem", "Den Helder", "'s-Gravenhage", "Rotterdam", "Dordrecht", "Leiden", "Middelburg", "Tilburg", "'s-Hertogenbosch", "Maastricht", "Bonaire"], "naam": "Joke de Kock", "achternaam": "de Kock", "voorletters": "J.C.M.", "voornaam": "Joke", "geslacht": "v", "stad": "Terheijden", "partij_naam": "Partij van de Arbeid (P.v.d.A.)", "tweede_poging": true, "vorige_partij": ""}, "Yasin Torunoglu": {"lijstnummer": 40, "kieskringen": ["Groningen", "Leeuwarden", "Assen", "Zwolle", "Lelystad", "Nijmegen", "Arnhem", "Utrecht", "Amsterdam", "Haarlem", "Den Helder", "'s-Gravenhage", "Rotterdam", "Dordrecht", "Leiden", "Middelburg", "Tilburg", "'s-Hertogenbosch", "Maastricht", "Bonaire"], "naam": "Yasin Torunoglu", "achternaam": "Torunoglu", "voorletters": "Y.", "voornaam": "Yasin", "geslacht": "m", "stad": "Eindhoven", "partij_naam": "Partij van de Arbeid (P.v.d.A.)", "tweede_poging": false, "vorige_partij": ""}, "Aya Selman": {"lijstnummer": 41, "kieskringen": ["Groningen", "Leeuwarden", "Assen", "Zwolle", "Lelystad", "Nijmegen", "Arnhem", "Utrecht", "Amsterdam", "Haarlem", "Den Helder", "'s-Gravenhage", "Rotterdam", "Dordrecht", "Leiden", "Middelburg", "Tilburg", "'s-Hertogenbosch", "Maastricht", "Bonaire"], "naam": "Aya Selman", "achternaam": "Selman", "voorletters": "A.", "voornaam": "Aya", "geslacht": "v", "stad": "Almere", "partij_naam": "Partij van de Arbeid (P.v.d.A.)", "tweede_poging": false, "vorige_partij": ""}, "Marc Newsome": {"lijstnummer": 42, "kieskringen": ["Groningen", "Leeuwarden", "Assen", "Zwolle", "Lelystad", "Nijmegen", "Arnhem", "Utrecht", "Amsterdam", "Haarlem", "Den Helder", "'s-Gravenhage", "Rotterdam", "Dordrecht", "Leiden", "Middelburg", "Tilburg", "'s-Hertogenbosch", "Maastricht", "Bonaire"], "naam": "Marc Newsome", "achternaam": "Newsome", "voorletters": "M.", "voornaam": "Marc", "geslacht": "m", "stad": "Leiden", "partij_naam": "Partij van de Arbeid (P.v.d.A.)", "tweede_poging": false, "vorige_partij": ""}, "Yara Hümmels": {"lijstnummer": 43, "kieskringen": ["Groningen", "Leeuwarden", "Assen", "Zwolle", "Lelystad", "Nijmegen", "Arnhem", "Utrecht", "Amsterdam", "Haarlem", "Den Helder", "'s-Gravenhage", "Rotterdam", "Dordrecht", "Leiden", "Middelburg", "Tilburg", "'s-Hertogenbosch", "Maastricht", "Bonaire"], "naam": "Yara Hümmels", "achternaam": "Hümmels", "voorletters": "Y.A.", "voornaam": "Yara", "geslacht": "v", "stad": "Enschede", "partij_naam": "Partij van de Arbeid (P.v.d.A.)", "tweede_poging": false, "vorige_partij": ""}, "Marco Eestermans": {"lijstnummer": 44, "kieskringen": ["Groningen", "Leeuwarden", "Assen", "Zwolle", "Lelystad", "Nijmegen", "Arnhem", "Utrecht", "Amsterdam", "Haarlem", "Den Helder", "'s-Gravenhage", "Rotterdam", "Dordrecht", "Leiden", "Middelburg", "Tilburg", "'s-Hertogenbosch", "Maastricht", "Bonaire"], "naam": "Marco Eestermans", "achternaam": "Eestermans", "voorletters": "M.", "voornaam": "Marco", "geslacht": "m", "stad": "Kloetinge", "partij_naam": "Partij van de Arbeid (P.v.d.A.)", "tweede_poging": false, "vorige_partij": ""}, "Peter Zwiers": {"lijstnummer": 45, "kieskringen": ["Groningen", "Leeuwarden", "Assen", "Zwolle", "Lelystad", "Nijmegen", "Arnhem", "Utrecht", "Amsterdam", "Haarlem", "Den Helder", "'s-Gravenhage", "Rotterdam", "Dordrecht", "Leiden", "Middelburg", "Tilburg", "'s-Hertogenbosch", "Maastricht", "Bonaire"], "naam": "Peter Zwiers", "achternaam": "Zwiers", "voorletters": "P.A.", "voornaam": "Peter", "geslacht": "m", "stad": "2e Exloërmond", "partij_naam": "Partij van de Arbeid (P.v.d.A.)", "tweede_poging": false, "vorige_partij": ""}, "Michiel Emmelkamp": {"lijstnummer": 46, "kieskringen": ["Groningen", "Leeuwarden", "Assen", "Zwolle", "Lelystad", "Nijmegen", "Arnhem", "Utrecht", "Amsterdam", "Haarlem", "Den Helder", "'s-Gravenhage", "Rotterdam", "Dordrecht", "Leiden", "Middelburg", "Tilburg", "'s-Hertogenbosch", "Maastricht", "Bonaire"], "naam": "Michiel Emmelkamp", "achternaam": "Emmelkamp", "voorletters": "M.D.", "voornaam": "Michiel", "geslacht": "m", "stad": "Amsterdam", "partij_naam": "Partij van de Arbeid (P.v.d.A.)", "tweede_poging": false, "vorige_partij": ""}, "Amma Asante": {"lijstnummer": 47, "kieskringen": ["Groningen", "Leeuwarden", "Assen", "Zwolle", "Lelystad", "Nijmegen", "Arnhem", "Utrecht", "Amsterdam", "Haarlem", "Den Helder", "'s-Gravenhage", "Rotterdam", "Dordrecht", "Leiden", "Middelburg", "Tilburg", "'s-Hertogenbosch", "Maastricht", "Bonaire"], "naam": "Amma Asante", "achternaam": "Asante", "voorletters": "A.A.", "voornaam": "Amma", "geslacht": "v", "stad": "Badhoevedorp", "partij_naam": "Partij van de Arbeid (P.v.d.A.)", "tweede_poging": true, "vorige_partij": ""}, "Tjeerd van Dekken": {"lijstnummer": 48, "kieskringen": ["Groningen"], "naam": "Tjeerd van Dekken", "achternaam": "van Dekken", "voorletters": "T.R.", "voornaam": "Tjeerd", "geslacht": "m", "stad": "Groningen", "partij_naam": "Partij van de Arbeid (P.v.d.A.)", "tweede_poging": true, "vorige_partij": ""}, "Laura Broekhuizen": {"lijstnummer": 49, "kieskringen": ["Groningen"], "naam": "Laura Broekhuizen", "achternaam": "Broekhuizen", "voorletters": "L.K.", "voornaam": "Laura", "geslacht": "v", "stad": "Winschoten", "partij_naam": "Partij van de Arbeid (P.v.d.A.)", "tweede_poging": false, "vorige_partij": ""}, "Bé Schollema": {"lijstnummer": 50, "kieskringen": ["Groningen"], "naam": "Bé Schollema", "achternaam": "Schollema", "voorletters": "B.", "voornaam": "Bé", "geslacht": "m", "stad": "Middelstum", "partij_naam": "Partij van de Arbeid (P.v.d.A.)", "tweede_poging": true, "vorige_partij": ""}, "Sjoerd Feitsma": {"lijstnummer": 48, "kieskringen": ["Leeuwarden"], "naam": "Sjoerd Feitsma", "achternaam": "Feitsma", "voorletters": "S.R.", "voornaam": "Sjoerd", "geslacht": "m", "stad": "Leeuwarden", "partij_naam": "Partij van de Arbeid (P.v.d.A.)", "tweede_poging": false, "vorige_partij": ""}, "Houkje Rijpstra": {"lijstnummer": 49, "kieskringen": ["Leeuwarden"], "naam": "Houkje Rijpstra", "achternaam": "Rijpstra", "voorletters": "H.", "voornaam": "Houkje", "geslacht": "v", "stad": "Gytsjerk", "partij_naam": "Partij van de Arbeid (P.v.d.A.)", "tweede_poging": true, "vorige_partij": ""}, "Stella van Gent": {"lijstnummer": 50, "kieskringen": ["Leeuwarden"], "naam": "Stella van Gent", "achternaam": "van Gent", "voorletters": "S.C.", "voornaam": "Stella", "geslacht": "v", "stad": "Sneek", "partij_naam": "Partij van de Arbeid (P.v.d.A.)", "tweede_poging": false, "vorige_partij": ""}, "Roelie Goettsch": {"lijstnummer": 48, "kieskringen": ["Assen"], "naam": "Roelie Goettsch", "achternaam": "Goettsch", "voorletters": "R.S.", "voornaam": "Roelie", "geslacht": "v", "stad": "Assen", "partij_naam": "Partij van de Arbeid (P.v.d.A.)", "tweede_poging": false, "vorige_partij": ""}, "Mark Tuit": {"lijstnummer": 49, "kieskringen": ["Assen"], "naam": "Mark Tuit", "achternaam": "Tuit", "voorletters": "A.M.", "voornaam": "Mark", "geslacht": "m", "stad": "Hollandscheveld", "partij_naam": "Partij van de Arbeid (P.v.d.A.)", "tweede_poging": false, "vorige_partij": ""}, "Janny Roggen": {"lijstnummer": 50, "kieskringen": ["Assen"], "naam": "Janny Roggen", "achternaam": "Roggen", "voorletters": "J.A.", "voornaam": "Janny", "geslacht": "v", "stad": "Vries", "partij_naam": "Partij van de Arbeid (P.v.d.A.)", "tweede_poging": false, "vorige_partij": ""}, "Theo Schouten": {"lijstnummer": 48, "kieskringen": ["Zwolle"], "naam": "Theo Schouten", "achternaam": "Schouten", "voorletters": "T.J.", "voornaam": "Theo", "geslacht": "m", "stad": "Almelo", "partij_naam": "Partij van de Arbeid (P.v.d.A.)", "tweede_poging": false, "vorige_partij": ""}, "Eefke Meijerink": {"lijstnummer": 49, "kieskringen": ["Zwolle"], "naam": "Eefke Meijerink", "achternaam": "Meijerink", "voorletters": "E.G.", "voornaam": "Eefke", "geslacht": "v", "stad": "Zwolle", "partij_naam": "Partij van de Arbeid (P.v.d.A.)", "tweede_poging": false, "vorige_partij": ""}, "Drees Kroes": {"lijstnummer": 50, "kieskringen": ["Zwolle"], "naam": "Drees Kroes", "achternaam": "Kroes", "voorletters": "D.", "voornaam": "Drees", "geslacht": "m", "stad": "Hengelo", "partij_naam": "Partij van de Arbeid (P.v.d.A.)", "tweede_poging": false, "vorige_partij": ""}, "Willem de Jager": {"lijstnummer": 48, "kieskringen": ["Lelystad"], "naam": "Willem de Jager", "achternaam": "de Jager", "voorletters": "W.", "voornaam": "Willem", "geslacht": "m", "stad": "Lelystad", "partij_naam": "Partij van de Arbeid (P.v.d.A.)", "tweede_poging": false, "vorige_partij": ""}, "Dania Al-Obaidi": {"lijstnummer": 49, "kieskringen": ["Lelystad"], "naam": "Dania Al-Obaidi", "achternaam": "Al-Obaidi", "voorletters": "D.", "voornaam": "Dania", "geslacht": "v", "stad": "Almere", "partij_naam": "Partij van de Arbeid (P.v.d.A.)", "tweede_poging": false, "vorige_partij": ""}, "Rien van der Velde": {"lijstnummer": 50, "kieskringen": ["Lelystad"], "naam": "Rien van der Velde", "achternaam": "van der Velde", "voorletters": "R.", "voornaam": "Rien", "geslacht": "m", "stad": "Emmeloord", "partij_naam": "Partij van de Arbeid (P.v.d.A.)", "tweede_poging": true, "vorige_partij": ""}, "Marinka Mulder": {"lijstnummer": 48, "kieskringen": ["Nijmegen", "Arnhem"], "naam": "Marinka Mulder", "achternaam": "Mulder", "voorletters": "M.A.", "voornaam": "Marinka", "geslacht": "v", "stad": "Oosterbeek", "partij_naam": "Partij van de Arbeid (P.v.d.A.)", "tweede_poging": true, "vorige_partij": ""}, "Rita Weeda": {"lijstnummer": 49, "kieskringen": ["Nijmegen"], "naam": "Rita Weeda", "achternaam": "Weeda", "voorletters": "H.J.", "voornaam": "Rita", "geslacht": "v", "stad": "Renkum", "partij_naam": "Partij van de Arbeid (P.v.d.A.)", "tweede_poging": true, "vorige_partij": ""}, "Peter Kerris": {"lijstnummer": 50, "kieskringen": ["Nijmegen", "Arnhem"], "naam": "Peter Kerris", "achternaam": "Kerris", "voorletters": "P.G.J.", "voornaam": "Peter", "geslacht": "m", "stad": "Nijmegen", "partij_naam": "Partij van de Arbeid (P.v.d.A.)", "tweede_poging": false, "vorige_partij": ""}, "Anne Janssen": {"lijstnummer": 49, "kieskringen": ["Arnhem"], "naam": "Anne Janssen", "achternaam": "Janssen", "voorletters": "A.M.E.", "voornaam": "Anne", "geslacht": "v", "stad": "Wageningen", "partij_naam": "Partij van de Arbeid (P.v.d.A.)", "tweede_poging": false, "vorige_partij": ""}, "Julie d' Hondt": {"lijstnummer": 48, "kieskringen": ["Utrecht"], "naam": "Julie d' Hondt", "achternaam": "d' Hondt", "voorletters": "J.P.", "voornaam": "Julie", "geslacht": "v", "stad": "Utrecht", "partij_naam": "Partij van de Arbeid (P.v.d.A.)", "tweede_poging": false, "vorige_partij": ""}, "Rob van Muilekom": {"lijstnummer": 49, "kieskringen": ["Utrecht"], "naam": "Rob van Muilekom", "achternaam": "van Muilekom", "voorletters": "R.G.H.", "voornaam": "Rob", "geslacht": "m", "stad": "Amersfoort", "partij_naam": "Partij van de Arbeid (P.v.d.A.)", "tweede_poging": false, "vorige_partij": ""}, "Hans Spekman": {"lijstnummer": 50, "kieskringen": ["Utrecht"], "naam": "Hans Spekman", "achternaam": "Spekman", "voorletters": "J.L.", "voornaam": "Hans", "geslacht": "m", "stad": "Utrecht", "partij_naam": "Partij van de Arbeid (P.v.d.A.)", "tweede_poging": true, "vorige_partij": ""}, "Carolien Gehrels": {"lijstnummer": 48, "kieskringen": ["Amsterdam"], "naam": "Carolien Gehrels", "achternaam": "Gehrels", "voorletters": "C.G.", "voornaam": "Carolien", "geslacht": "v", "stad": "Amsterdam", "partij_naam": "Partij van de Arbeid (P.v.d.A.)", "tweede_poging": false, "vorige_partij": ""}, "Elvira Sweet": {"lijstnummer": 49, "kieskringen": ["Amsterdam"], "naam": "Elvira Sweet", "achternaam": "Sweet", "voorletters": "E.M.", "voornaam": "Elvira", "geslacht": "v", "stad": "Amsterdam", "partij_naam": "Partij van de Arbeid (P.v.d.A.)", "tweede_poging": false, "vorige_partij": ""}, "Hedy d' Ancona": {"lijstnummer": 50, "kieskringen": ["Amsterdam", "Haarlem", "Bonaire"], "naam": "Hedy d' Ancona", "achternaam": "d' Ancona", "voorletters": "H.", "voornaam": "Hedy", "geslacht": "v", "stad": "Amsterdam", "partij_naam": "Partij van de Arbeid (P.v.d.A.)", "tweede_poging": true, "vorige_partij": ""}, "Xander den Uyl": {"lijstnummer": 48, "kieskringen": ["Haarlem"], "naam": "Xander den Uyl", "achternaam": "den Uyl", "voorletters": "X.J.", "voornaam": "Xander", "geslacht": "m", "stad": "Haarlem", "partij_naam": "Partij van de Arbeid (P.v.d.A.)", "tweede_poging": true, "vorige_partij": ""}, "Peter de Vrij": {"lijstnummer": 48, "kieskringen": ["Den Helder"], "naam": "Peter de Vrij", "achternaam": "de Vrij", "voorletters": "P.", "voornaam": "Peter", "geslacht": "m", "stad": "Den Helder", "partij_naam": "Partij van de Arbeid (P.v.d.A.)", "tweede_poging": false, "vorige_partij": ""}, "Paul Verbruggen": {"lijstnummer": 49, "kieskringen": ["Den Helder"], "naam": "Paul Verbruggen", "achternaam": "Verbruggen", "voorletters": "P.G.M.", "voornaam": "Paul", "geslacht": "m", "stad": "Alkmaar", "partij_naam": "Partij van de Arbeid (P.v.d.A.)", "tweede_poging": false, "vorige_partij": ""}, "Stefan Brau": {"lijstnummer": 50, "kieskringen": ["Den Helder"], "naam": "Stefan Brau", "achternaam": "Brau", "voorletters": "S.", "voornaam": "Stefan", "geslacht": "m", "stad": "Heerhugowaard", "partij_naam": "Partij van de Arbeid (P.v.d.A.)", "tweede_poging": false, "vorige_partij": ""}, "Samir Ahraui": {"lijstnummer": 48, "kieskringen": ["'s-Gravenhage"], "naam": "Samir Ahraui", "achternaam": "Ahraui", "voorletters": "S.", "voornaam": "Samir", "geslacht": "m", "stad": "'s-Gravenhage", "partij_naam": "Partij van de Arbeid (P.v.d.A.)", "tweede_poging": false, "vorige_partij": ""}, "Marit Maij": {"lijstnummer": 49, "kieskringen": ["'s-Gravenhage"], "naam": "Marit Maij", "achternaam": "Maij", "voorletters": "M.E.", "voornaam": "Marit", "geslacht": "v", "stad": "'s-Gravenhage", "partij_naam": "Partij van de Arbeid (P.v.d.A.)", "tweede_poging": true, "vorige_partij": ""}, "Jeltje van Nieuwenhoven": {"lijstnummer": 50, "kieskringen": ["'s-Gravenhage"], "naam": "Jeltje van Nieuwenhoven", "achternaam": "van Nieuwenhoven", "voorletters": "J.", "voornaam": "Jeltje", "geslacht": "v", "stad": "'s-Gravenhage", "partij_naam": "Partij van de Arbeid (P.v.d.A.)", "tweede_poging": true, "vorige_partij": ""}, "Steven Lammering": {"lijstnummer": 48, "kieskringen": ["Rotterdam"], "naam": "Steven Lammering", "achternaam": "Lammering", "voorletters": "S.F.", "voornaam": "Steven", "geslacht": "m", "stad": "Rotterdam", "partij_naam": "Partij van de Arbeid (P.v.d.A.)", "tweede_poging": false, "vorige_partij": ""}, "Richard Moti": {"lijstnummer": 49, "kieskringen": ["Rotterdam"], "naam": "Richard Moti", "achternaam": "Moti", "voorletters": "R.", "voornaam": "Richard", "geslacht": "m", "stad": "Rotterdam", "partij_naam": "Partij van de Arbeid (P.v.d.A.)", "tweede_poging": true, "vorige_partij": ""}, "Hamit Karakus": {"lijstnummer": 50, "kieskringen": ["Rotterdam"], "naam": "Hamit Karakus", "achternaam": "Karakus", "voorletters": "H.", "voornaam": "Hamit", "geslacht": "m", "stad": "Rotterdam", "partij_naam": "Partij van de Arbeid (P.v.d.A.)", "tweede_poging": false, "vorige_partij": ""}, "Hayri Yildiz": {"lijstnummer": 48, "kieskringen": ["Dordrecht"], "naam": "Hayri Yildiz", "achternaam": "Yildiz", "voorletters": "H.K.P.", "voornaam": "Hayri", "geslacht": "m", "stad": "Delft", "partij_naam": "Partij van de Arbeid (P.v.d.A.)", "tweede_poging": false, "vorige_partij": ""}, "Reshma Roopram": {"lijstnummer": 49, "kieskringen": ["Dordrecht"], "naam": "Reshma Roopram", "achternaam": "Roopram", "voorletters": "R.D.", "voornaam": "Reshma", "geslacht": "v", "stad": "Barendrecht", "partij_naam": "Partij van de Arbeid (P.v.d.A.)", "tweede_poging": true, "vorige_partij": ""}, "Wouter Struijk": {"lijstnummer": 50, "kieskringen": ["Dordrecht"], "naam": "Wouter Struijk", "achternaam": "Struijk", "voorletters": "W.", "voornaam": "Wouter", "geslacht": "m", "stad": "Spijkenisse", "partij_naam": "Partij van de Arbeid (P.v.d.A.)", "tweede_poging": true, "vorige_partij": ""}, "Sophie Heesen": {"lijstnummer": 48, "kieskringen": ["Leiden"], "naam": "Sophie Heesen", "achternaam": "Heesen", "voorletters": "S.L.W.", "voornaam": "Sophie", "geslacht": "v", "stad": "Gouda", "partij_naam": "Partij van de Arbeid (P.v.d.A.)", "tweede_poging": false, "vorige_partij": ""}, "Rosalie Bedijn": {"lijstnummer": 49, "kieskringen": ["Leiden"], "naam": "Rosalie Bedijn", "achternaam": "Bedijn", "voorletters": "R.M.", "voornaam": "Rosalie", "geslacht": "v", "stad": "Noordwijk", "partij_naam": "Partij van de Arbeid (P.v.d.A.)", "tweede_poging": false, "vorige_partij": ""}, "Abdelhaq Jermoumi": {"lijstnummer": 50, "kieskringen": ["Leiden"], "naam": "Abdelhaq Jermoumi", "achternaam": "Jermoumi", "voorletters": "A.", "voornaam": "Abdelhaq", "geslacht": "m", "stad": "Leiden", "partij_naam": "Partij van de Arbeid (P.v.d.A.)", "tweede_poging": false, "vorige_partij": ""}, "Laszlo van de Voorde": {"lijstnummer": 48, "kieskringen": ["Middelburg"], "naam": "Laszlo van de Voorde", "achternaam": "van de Voorde", "voorletters": "L.", "voornaam": "Laszlo", "geslacht": "m", "stad": "Zaamslag", "partij_naam": "Partij van de Arbeid (P.v.d.A.)", "tweede_poging": false, "vorige_partij": ""}, "Chris Maas": {"lijstnummer": 49, "kieskringen": ["Middelburg"], "naam": "Chris Maas", "achternaam": "Maas", "voorletters": "C.", "voornaam": "Chris", "geslacht": "m", "stad": "Domburg", "partij_naam": "Partij van de Arbeid (P.v.d.A.)", "tweede_poging": true, "vorige_partij": ""}, "Kees Verburg": {"lijstnummer": 50, "kieskringen": ["Middelburg"], "naam": "Kees Verburg", "achternaam": "Verburg", "voorletters": "C.A.", "voornaam": "Kees", "geslacht": "m", "stad": "Hansweert", "partij_naam": "Partij van de Arbeid (P.v.d.A.)", "tweede_poging": false, "vorige_partij": ""}, "Adam Ahajaj": {"lijstnummer": 48, "kieskringen": ["Tilburg"], "naam": "Adam Ahajaj", "achternaam": "Ahajaj", "voorletters": "A.", "voornaam": "Adam", "geslacht": "m", "stad": "Bergen op Zoom", "partij_naam": "Partij van de Arbeid (P.v.d.A.)", "tweede_poging": false, "vorige_partij": ""}, "Bea Mieris": {"lijstnummer": 49, "kieskringen": ["Tilburg"], "naam": "Bea Mieris", "achternaam": "Mieris", "voorletters": "P.L.R.", "voornaam": "Bea", "geslacht": "v", "stad": "Tilburg", "partij_naam": "Partij van de Arbeid (P.v.d.A.)", "tweede_poging": false, "vorige_partij": ""}, "Arjen van Drunen": {"lijstnummer": 50, "kieskringen": ["Tilburg"], "naam": "Arjen van Drunen", "achternaam": "van Drunen", "voorletters": "A.M.A.", "voornaam": "Arjen", "geslacht": "m", "stad": "Teteringen", "partij_naam": "Partij van de Arbeid (P.v.d.A.)", "tweede_poging": false, "vorige_partij": ""}, "Sultan Günal-Gezer": {"lijstnummer": 48, "kieskringen": ["'s-Hertogenbosch"], "naam": "Sultan Günal-Gezer", "achternaam": "Günal-Gezer", "voorletters": "S.", "voornaam": "Sultan", "geslacht": "v", "stad": "Uden", "partij_naam": "Partij van de Arbeid (P.v.d.A.)", "tweede_poging": true, "vorige_partij": ""}, "Antoinette Knoet": {"lijstnummer": 49, "kieskringen": ["'s-Hertogenbosch"], "naam": "Antoinette Knoet", "achternaam": "Knoet", "voorletters": "A.J.H.", "voornaam": "Antoinette", "geslacht": "v", "stad": "Vlierden", "partij_naam": "Partij van de Arbeid (P.v.d.A.)", "tweede_poging": false, "vorige_partij": ""}, "Erik van Merrienboer": {"lijstnummer": 50, "kieskringen": ["'s-Hertogenbosch"], "naam": "Erik van Merrienboer", "achternaam": "van Merrienboer", "voorletters": "H.J.A.", "voornaam": "Erik", "geslacht": "m", "stad": "Eindhoven", "partij_naam": "Partij van de Arbeid (P.v.d.A.)", "tweede_poging": false, "vorige_partij": ""}, "Merle van Leusden-Brüning": {"lijstnummer": 48, "kieskringen": ["Maastricht"], "naam": "Merle van Leusden-Brüning", "achternaam": "van Leusden-Brüning", "voorletters": "M.Y.", "voornaam": "Merle", "geslacht": "v", "stad": "Brunssum", "partij_naam": "Partij van de Arbeid (P.v.d.A.)", "tweede_poging": false, "vorige_partij": ""}, "Manon Fokke": {"lijstnummer": 49, "kieskringen": ["Maastricht"], "naam": "Manon Fokke", "achternaam": "Fokke", "voorletters": "H.", "voornaam": "Manon", "geslacht": "v", "stad": "Maastricht", "partij_naam": "Partij van de Arbeid (P.v.d.A.)", "tweede_poging": false, "vorige_partij": ""}, "Jan Smeets": {"lijstnummer": 50, "kieskringen": ["Maastricht"], "naam": "Jan Smeets", "achternaam": "Smeets", "voorletters": "J.A.P.", "voornaam": "Jan", "geslacht": "m", "stad": "Sittard", "partij_naam": "Partij van de Arbeid (P.v.d.A.)", "tweede_poging": true, "vorige_partij": ""}, "John Leerdam": {"lijstnummer": 48, "kieskringen": ["Bonaire"], "naam": "John Leerdam", "achternaam": "Leerdam", "voorletters": "J.A.W.J.", "voornaam": "John", "geslacht": "m", "stad": "Amsterdam", "partij_naam": "Partij van de Arbeid (P.v.d.A.)", "tweede_poging": true, "vorige_partij": ""}}