{"Mark Rutte": {"lijstnummer": 1, "kieskringen": ["Groningen", "Leeuwarden", "Assen", "Zwolle", "Lelystad", "Nijmegen", "Arnhem", "Utrecht", "Amsterdam", "Haarlem", "Den Helder", "'s-Gravenhage", "Rotterdam", "Dordrecht", "Leiden", "Middelburg", "Tilburg", "'s-Hertogenbosch", "Maastricht", "Bonaire"], "naam": "Mark Rutte", "achternaam": "Rutte", "voorletters": "M.", "voornaam": "Mark", "geslacht": "m", "stad": "'s-Gravenhage", "partij_naam": "VVD", "tweede_poging": true, "vorige_partij": ""}, "Tamara van Ark": {"lijstnummer": 2, "kieskringen": ["Groningen", "Leeuwarden", "Assen", "Zwolle", "Lelystad", "Nijmegen", "Arnhem", "Utrecht", "Amsterdam", "Haarlem", "Den Helder", "'s-Gravenhage", "Rotterdam", "Dordrecht", "Leiden", "Middelburg", "Tilburg", "'s-Hertogenbosch", "Maastricht", "Bonaire"], "naam": "Tamara van Ark", "achternaam": "van Ark", "voorletters": "T.", "voornaam": "Tamara", "geslacht": "v", "stad": "Nieuwerkerk aan den IJssel", "partij_naam": "VVD", "tweede_poging": true, "vorige_partij": ""}, "Sophie Hermans": {"lijstnummer": 3, "kieskringen": ["Groningen", "Leeuwarden", "Assen", "Zwolle", "Lelystad", "Nijmegen", "Arnhem", "Utrecht", "Amsterdam", "Haarlem", "Den Helder", "'s-Gravenhage", "Rotterdam", "Dordrecht", "Leiden", "Middelburg", "Tilburg", "'s-Hertogenbosch", "Maastricht", "Bonaire"], "naam": "Sophie Hermans", "achternaam": "Hermans", "voorletters": "S.T.M.", "voornaam": "Sophie", "geslacht": "v", "stad": "Amsterdam", "partij_naam": "VVD", "tweede_poging": true, "vorige_partij": ""}, "Bente Becker": {"lijstnummer": 4, "kieskringen": ["Groningen", "Leeuwarden", "Assen", "Zwolle", "Lelystad", "Nijmegen", "Arnhem", "Utrecht", "Amsterdam", "Haarlem", "Den Helder", "'s-Gravenhage", "Rotterdam", "Dordrecht", "Leiden", "Middelburg", "Tilburg", "'s-Hertogenbosch", "Maastricht", "Bonaire"], "naam": "Bente Becker", "achternaam": "Becker", "voorletters": "B.", "voornaam": "Bente", "geslacht": "v", "stad": "'s-Gravenhage", "partij_naam": "VVD", "tweede_poging": true, "vorige_partij": ""}, "Dilan Ye\u015filg\u00f6z-Zegerius": {"lijstnummer": 5, "kieskringen": ["Groningen", "Leeuwarden", "Assen", "Zwolle", "Lelystad", "Nijmegen", "Arnhem", "Utrecht", "Amsterdam", "Haarlem", "Den Helder", "'s-Gravenhage", "Rotterdam", "Dordrecht", "Leiden", "Middelburg", "Tilburg", "'s-Hertogenbosch", "Maastricht", "Bonaire"], "naam": "Dilan Ye\u015filg\u00f6z-Zegerius", "achternaam": "Ye\u015filg\u00f6z-Zegerius", "voorletters": "D.", "voornaam": "Dilan", "geslacht": "v", "stad": "Amsterdam", "partij_naam": "VVD", "tweede_poging": true, "vorige_partij": ""}, "Bas van 't Wout": {"lijstnummer": 6, "kieskringen": ["Groningen", "Leeuwarden", "Assen", "Zwolle", "Lelystad", "Nijmegen", "Arnhem", "Utrecht", "Amsterdam", "Haarlem", "Den Helder", "'s-Gravenhage", "Rotterdam", "Dordrecht", "Leiden", "Middelburg", "Tilburg", "'s-Hertogenbosch", "Maastricht", "Bonaire"], "naam": "Bas van 't Wout", "achternaam": "van 't Wout", "voorletters": "B.", "voornaam": "Bas", "geslacht": "m", "stad": "Hoeven", "partij_naam": "VVD", "tweede_poging": true, "vorige_partij": ""}, "Mark Harbers": {"lijstnummer": 7, "kieskringen": ["Groningen", "Leeuwarden", "Assen", "Zwolle", "Lelystad", "Nijmegen", "Arnhem", "Utrecht", "Amsterdam", "Haarlem", "Den Helder", "'s-Gravenhage", "Rotterdam", "Dordrecht", "Leiden", "Middelburg", "Tilburg", "'s-Hertogenbosch", "Maastricht", "Bonaire"], "naam": "Mark Harbers", "achternaam": "Harbers", "voorletters": "M.G.J.", "voornaam": "Mark", "geslacht": "m", "stad": "Rotterdam", "partij_naam": "VVD", "tweede_poging": true, "vorige_partij": ""}, "Aukje de Vries": {"lijstnummer": 8, "kieskringen": ["Groningen", "Leeuwarden", "Assen", "Zwolle", "Lelystad", "Nijmegen", "Arnhem", "Utrecht", "Amsterdam", "Haarlem", "Den Helder", "'s-Gravenhage", "Rotterdam", "Dordrecht", "Leiden", "Middelburg", "Tilburg", "'s-Hertogenbosch", "Maastricht", "Bonaire"], "naam": "Aukje de Vries", "achternaam": "de Vries", "voorletters": "A.", "voornaam": "Aukje", "geslacht": "v", "stad": "Leeuwarden", "partij_naam": "VVD", "tweede_poging": true, "vorige_partij": ""}, "Dennis Wiersma": {"lijstnummer": 9, "kieskringen": ["Groningen", "Leeuwarden", "Assen", "Zwolle", "Lelystad", "Nijmegen", "Arnhem", "Utrecht", "Amsterdam", "Haarlem", "Den Helder", "'s-Gravenhage", "Rotterdam", "Dordrecht", "Leiden", "Middelburg", "Tilburg", "'s-Hertogenbosch", "Maastricht", "Bonaire"], "naam": "Dennis Wiersma", "achternaam": "Wiersma", "voorletters": "A.D.", "voornaam": "Dennis", "geslacht": "m", "stad": "Utrecht", "partij_naam": "VVD", "tweede_poging": true, "vorige_partij": ""}, "Ockje Tellegen": {"lijstnummer": 10, "kieskringen": ["Groningen", "Leeuwarden", "Assen", "Zwolle", "Lelystad", "Nijmegen", "Arnhem", "Utrecht", "Amsterdam", "Haarlem", "Den Helder", "'s-Gravenhage", "Rotterdam", "Dordrecht", "Leiden", "Middelburg", "Tilburg", "'s-Hertogenbosch", "Maastricht", "Bonaire"], "naam": "Ockje Tellegen", "achternaam": "Tellegen", "voorletters": "O.C.", "voornaam": "Ockje", "geslacht": "v", "stad": "'s-Gravenhage", "partij_naam": "VVD", "tweede_poging": true, "vorige_partij": ""}, "Thierry Aartsen": {"lijstnummer": 11, "kieskringen": ["Groningen", "Leeuwarden", "Assen", "Zwolle", "Lelystad", "Nijmegen", "Arnhem", "Utrecht", "Amsterdam", "Haarlem", "Den Helder", "'s-Gravenhage", "Rotterdam", "Dordrecht", "Leiden", "Middelburg", "Tilburg", "'s-Hertogenbosch", "Maastricht", "Bonaire"], "naam": "Thierry Aartsen", "achternaam": "Aartsen", "voorletters": "A.A.", "voornaam": "Thierry", "geslacht": "m", "stad": "Breda", "partij_naam": "VVD", "tweede_poging": true, "vorige_partij": ""}, "Eelco Heinen": {"lijstnummer": 12, "kieskringen": ["Groningen", "Leeuwarden", "Assen", "Zwolle", "Lelystad", "Nijmegen", "Arnhem", "Utrecht", "Amsterdam", "Haarlem", "Den Helder", "'s-Gravenhage", "Rotterdam", "Dordrecht", "Leiden", "Middelburg", "Tilburg", "'s-Hertogenbosch", "Maastricht", "Bonaire"], "naam": "Eelco Heinen", "achternaam": "Heinen", "voorletters": "E.", "voornaam": "Eelco", "geslacht": "m", "stad": "'s-Gravenhage", "partij_naam": "VVD", "tweede_poging": false, "vorige_partij": ""}, "Q.M. Rajkowski": {"lijstnummer": 13, "kieskringen": ["Groningen", "Leeuwarden", "Assen", "Zwolle", "Lelystad", "Nijmegen", "Arnhem", "Utrecht", "Amsterdam", "Haarlem", "Den Helder", "'s-Gravenhage", "Rotterdam", "Dordrecht", "Leiden", "Middelburg", "Tilburg", "'s-Hertogenbosch", "Maastricht", "Bonaire"], "naam": "Q.M. Rajkowski", "achternaam": "Rajkowski", "voorletters": "Q.M.", "voornaam": "", "geslacht": "v", "stad": "Utrecht", "partij_naam": "VVD", "tweede_poging": false, "vorige_partij": ""}, "Roelien Kamminga": {"lijstnummer": 14, "kieskringen": ["Groningen", "Leeuwarden", "Assen", "Zwolle", "Lelystad", "Nijmegen", "Arnhem", "Utrecht", "Amsterdam", "Haarlem", "Den Helder", "'s-Gravenhage", "Rotterdam", "Dordrecht", "Leiden", "Middelburg", "Tilburg", "'s-Hertogenbosch", "Maastricht", "Bonaire"], "naam": "Roelien Kamminga", "achternaam": "Kamminga", "voorletters": "R.J.", "voornaam": "Roelien", "geslacht": "v", "stad": "Groningen", "partij_naam": "VVD", "tweede_poging": false, "vorige_partij": ""}, "Zohair El Yassini": {"lijstnummer": 15, "kieskringen": ["Groningen", "Leeuwarden", "Assen", "Zwolle", "Lelystad", "Nijmegen", "Arnhem", "Utrecht", "Amsterdam", "Haarlem", "Den Helder", "'s-Gravenhage", "Rotterdam", "Dordrecht", "Leiden", "Middelburg", "Tilburg", "'s-Hertogenbosch", "Maastricht", "Bonaire"], "naam": "Zohair El Yassini", "achternaam": "El Yassini", "voorletters": "Z.", "voornaam": "Zohair", "geslacht": "m", "stad": "Utrecht", "partij_naam": "VVD", "tweede_poging": true, "vorige_partij": ""}, "Thom van Campen": {"lijstnummer": 16, "kieskringen": ["Groningen", "Leeuwarden", "Assen", "Zwolle", "Lelystad", "Nijmegen", "Arnhem", "Utrecht", "Amsterdam", "Haarlem", "Den Helder", "'s-Gravenhage", "Rotterdam", "Dordrecht", "Leiden", "Middelburg", "Tilburg", "'s-Hertogenbosch", "Maastricht", "Bonaire"], "naam": "Thom van Campen", "achternaam": "van Campen", "voorletters": "A.A.H.", "voornaam": "Thom", "geslacht": "m", "stad": "Zwolle", "partij_naam": "VVD", "tweede_poging": false, "vorige_partij": ""}, "Mari\u00eblle Paul": {"lijstnummer": 17, "kieskringen": ["Groningen", "Leeuwarden", "Assen", "Zwolle", "Lelystad", "Nijmegen", "Arnhem", "Utrecht", "Amsterdam", "Haarlem", "Den Helder", "'s-Gravenhage", "Rotterdam", "Dordrecht", "Leiden", "Middelburg", "Tilburg", "'s-Hertogenbosch", "Maastricht", "Bonaire"], "naam": "Mari\u00eblle Paul", "achternaam": "Paul", "voorletters": "M.L.J.", "voornaam": "Mari\u00eblle", "geslacht": "v", "stad": "Amsterdam", "partij_naam": "VVD", "tweede_poging": false, "vorige_partij": ""}, "Silvio Erkens": {"lijstnummer": 18, "kieskringen": ["Groningen", "Leeuwarden", "Assen", "Zwolle", "Lelystad", "Nijmegen", "Arnhem", "Utrecht", "Amsterdam", "Haarlem", "Den Helder", "'s-Gravenhage", "Rotterdam", "Dordrecht", "Leiden", "Middelburg", "Tilburg", "'s-Hertogenbosch", "Maastricht", "Bonaire"], "naam": "Silvio Erkens", "achternaam": "Erkens", "voorletters": "S.P.A.", "voornaam": "Silvio", "geslacht": "m", "stad": "Kerkrade", "partij_naam": "VVD", "tweede_poging": false, "vorige_partij": ""}, "Daniel Koerhuis": {"lijstnummer": 19, "kieskringen": ["Groningen", "Leeuwarden", "Assen", "Zwolle", "Lelystad", "Nijmegen", "Arnhem", "Utrecht", "Amsterdam", "Haarlem", "Den Helder", "'s-Gravenhage", "Rotterdam", "Dordrecht", "Leiden", "Middelburg", "Tilburg", "'s-Hertogenbosch", "Maastricht", "Bonaire"], "naam": "Daniel Koerhuis", "achternaam": "Koerhuis", "voorletters": "D.A.N.", "voornaam": "Daniel", "geslacht": "m", "stad": "Raalte", "partij_naam": "VVD", "tweede_poging": true, "vorige_partij": ""}, "Ingrid Michon-Derkzen": {"lijstnummer": 20, "kieskringen": ["Groningen", "Leeuwarden", "Assen", "Zwolle", "Lelystad", "Nijmegen", "Arnhem", "Utrecht", "Amsterdam", "Haarlem", "Den Helder", "'s-Gravenhage", "Rotterdam", "Dordrecht", "Leiden", "Middelburg", "Tilburg", "'s-Hertogenbosch", "Maastricht", "Bonaire"], "naam": "Ingrid Michon-Derkzen", "achternaam": "Michon-Derkzen", "voorletters": "I.J.M.", "voornaam": "Ingrid", "geslacht": "v", "stad": "'s-Gravenhage", "partij_naam": "VVD", "tweede_poging": false, "vorige_partij": ""}, "Peter Valstar": {"lijstnummer": 21, "kieskringen": ["Groningen", "Leeuwarden", "Assen", "Zwolle", "Lelystad", "Nijmegen", "Arnhem", "Utrecht", "Amsterdam", "Haarlem", "Den Helder", "'s-Gravenhage", "Rotterdam", "Dordrecht", "Leiden", "Middelburg", "Tilburg", "'s-Hertogenbosch", "Maastricht", "Bonaire"], "naam": "Peter Valstar", "achternaam": "Valstar", "voorletters": "P.J.", "voornaam": "Peter", "geslacht": "m", "stad": "'s-Gravenzande", "partij_naam": "VVD", "tweede_poging": false, "vorige_partij": ""}, "Ulysse Ellian": {"lijstnummer": 22, "kieskringen": ["Groningen", "Leeuwarden", "Assen", "Zwolle", "Lelystad", "Nijmegen", "Arnhem", "Utrecht", "Amsterdam", "Haarlem", "Den Helder", "'s-Gravenhage", "Rotterdam", "Dordrecht", "Leiden", "Middelburg", "Tilburg", "'s-Hertogenbosch", "Maastricht", "Bonaire"], "naam": "Ulysse Ellian", "achternaam": "Ellian", "voorletters": "U.", "voornaam": "Ulysse", "geslacht": "m", "stad": "Almere", "partij_naam": "VVD", "tweede_poging": false, "vorige_partij": ""}, "Jeroen Van Wijngaarden": {"lijstnummer": 23, "kieskringen": ["Groningen", "Leeuwarden", "Assen", "Zwolle", "Lelystad", "Nijmegen", "Arnhem", "Utrecht", "Amsterdam", "Haarlem", "Den Helder", "'s-Gravenhage", "Rotterdam", "Dordrecht", "Leiden", "Middelburg", "Tilburg", "'s-Hertogenbosch", "Maastricht", "Bonaire"], "naam": "Jeroen Van Wijngaarden", "achternaam": "Van Wijngaarden", "voorletters": "J.", "voornaam": "Jeroen", "geslacht": "m", "stad": "Amsterdam", "partij_naam": "VVD", "tweede_poging": true, "vorige_partij": ""}, "Peter de Groot": {"lijstnummer": 24, "kieskringen": ["Groningen", "Leeuwarden", "Assen", "Zwolle", "Lelystad", "Nijmegen", "Arnhem", "Utrecht", "Amsterdam", "Haarlem", "Den Helder", "'s-Gravenhage", "Rotterdam", "Dordrecht", "Leiden", "Middelburg", "Tilburg", "'s-Hertogenbosch", "Maastricht", "Bonaire"], "naam": "Peter de Groot", "achternaam": "de Groot", "voorletters": "P.C.", "voornaam": "Peter", "geslacht": "m", "stad": "Harderwijk", "partij_naam": "VVD", "tweede_poging": false, "vorige_partij": ""}, "Jacqueline van den Hil": {"lijstnummer": 25, "kieskringen": ["Groningen", "Leeuwarden", "Assen", "Zwolle", "Lelystad", "Nijmegen", "Arnhem", "Utrecht", "Amsterdam", "Haarlem", "Den Helder", "'s-Gravenhage", "Rotterdam", "Dordrecht", "Leiden", "Middelburg", "Tilburg", "'s-Hertogenbosch", "Maastricht", "Bonaire"], "naam": "Jacqueline van den Hil", "achternaam": "van den Hil", "voorletters": "J.", "voornaam": "Jacqueline", "geslacht": "v", "stad": "Goes", "partij_naam": "VVD", "tweede_poging": false, "vorige_partij": ""}, "Fahid Minhas": {"lijstnummer": 26, "kieskringen": ["Groningen", "Leeuwarden", "Assen", "Zwolle", "Lelystad", "Nijmegen", "Arnhem", "Utrecht", "Amsterdam", "Haarlem", "Den Helder", "'s-Gravenhage", "Rotterdam", "Dordrecht", "Leiden", "Middelburg", "Tilburg", "'s-Hertogenbosch", "Maastricht", "Bonaire"], "naam": "Fahid Minhas", "achternaam": "Minhas", "voorletters": "F.B.", "voornaam": "Fahid", "geslacht": "m", "stad": "Schiedam", "partij_naam": "VVD", "tweede_poging": false, "vorige_partij": ""}, "Judith Tielen": {"lijstnummer": 27, "kieskringen": ["Groningen", "Leeuwarden", "Assen", "Zwolle", "Lelystad", "Nijmegen", "Arnhem", "Utrecht", "Amsterdam", "Haarlem", "Den Helder", "'s-Gravenhage", "Rotterdam", "Dordrecht", "Leiden", "Middelburg", "Tilburg", "'s-Hertogenbosch", "Maastricht", "Bonaire"], "naam": "Judith Tielen", "achternaam": "Tielen", "voorletters": "J.Z.C.M.", "voornaam": "Judith", "geslacht": "v", "stad": "Utrecht", "partij_naam": "VVD", "tweede_poging": true, "vorige_partij": ""}, "Daan de Kort": {"lijstnummer": 28, "kieskringen": ["Groningen", "Leeuwarden", "Assen", "Zwolle", "Lelystad", "Nijmegen", "Arnhem", "Utrecht", "Amsterdam", "Haarlem", "Den Helder", "'s-Gravenhage", "Rotterdam", "Dordrecht", "Leiden", "Middelburg", "Tilburg", "'s-Hertogenbosch", "Maastricht", "Bonaire"], "naam": "Daan de Kort", "achternaam": "de Kort", "voorletters": "A.H.J.", "voornaam": "Daan", "geslacht": "m", "stad": "Veldhoven", "partij_naam": "VVD", "tweede_poging": false, "vorige_partij": ""}, "Rudmer Heerema": {"lijstnummer": 29, "kieskringen": ["Groningen", "Leeuwarden", "Assen", "Zwolle", "Lelystad", "Nijmegen", "Arnhem", "Utrecht", "Amsterdam", "Haarlem", "Den Helder", "'s-Gravenhage", "Rotterdam", "Dordrecht", "Leiden", "Middelburg", "Tilburg", "'s-Hertogenbosch", "Maastricht", "Bonaire"], "naam": "Rudmer Heerema", "achternaam": "Heerema", "voorletters": "R.J.", "voornaam": "Rudmer", "geslacht": "m", "stad": "Alkmaar", "partij_naam": "VVD", "tweede_poging": true, "vorige_partij": ""}, "Ruben Brekelmans": {"lijstnummer": 30, "kieskringen": ["Groningen", "Leeuwarden", "Assen", "Zwolle", "Lelystad", "Nijmegen", "Arnhem", "Utrecht", "Amsterdam", "Haarlem", "Den Helder", "'s-Gravenhage", "Rotterdam", "Dordrecht", "Leiden", "Middelburg", "Tilburg", "'s-Hertogenbosch", "Maastricht", "Bonaire"], "naam": "Ruben Brekelmans", "achternaam": "Brekelmans", "voorletters": "R.P.", "voornaam": "Ruben", "geslacht": "m", "stad": "Oisterwijk", "partij_naam": "VVD", "tweede_poging": false, "vorige_partij": ""}, "Pim van Strien": {"lijstnummer": 31, "kieskringen": ["Groningen", "Leeuwarden", "Assen", "Zwolle", "Lelystad", "Nijmegen", "Arnhem", "Utrecht", "Amsterdam", "Haarlem", "Den Helder", "'s-Gravenhage", "Rotterdam", "Dordrecht", "Leiden", "Middelburg", "Tilburg", "'s-Hertogenbosch", "Maastricht", "Bonaire"], "naam": "Pim van Strien", "achternaam": "van Strien", "voorletters": "P.J.T.", "voornaam": "Pim", "geslacht": "m", "stad": "Amsterdam", "partij_naam": "VVD", "tweede_poging": false, "vorige_partij": ""}, "Hatte van der Woude": {"lijstnummer": 32, "kieskringen": ["Groningen", "Leeuwarden", "Assen", "Zwolle", "Lelystad", "Nijmegen", "Arnhem", "Utrecht", "Amsterdam", "Haarlem", "Den Helder", "'s-Gravenhage", "Rotterdam", "Dordrecht", "Leiden", "Middelburg", "Tilburg", "'s-Hertogenbosch", "Maastricht", "Bonaire"], "naam": "Hatte van der Woude", "achternaam": "van der Woude", "voorletters": "H.H.", "voornaam": "Hatte", "geslacht": "v", "stad": "Delft", "partij_naam": "VVD", "tweede_poging": false, "vorige_partij": ""}, "Folkert Idsinga": {"lijstnummer": 33, "kieskringen": ["Groningen", "Leeuwarden", "Assen", "Zwolle", "Lelystad", "Nijmegen", "Arnhem", "Utrecht", "Amsterdam", "Haarlem", "Den Helder", "'s-Gravenhage", "Rotterdam", "Dordrecht", "Leiden", "Middelburg", "Tilburg", "'s-Hertogenbosch", "Maastricht", "Bonaire"], "naam": "Folkert Idsinga", "achternaam": "Idsinga", "voorletters": "F.L.", "voornaam": "Folkert", "geslacht": "m", "stad": "Amsterdam", "partij_naam": "VVD", "tweede_poging": false, "vorige_partij": ""}, "Daan de Neef": {"lijstnummer": 34, "kieskringen": ["Groningen", "Leeuwarden", "Assen", "Zwolle", "Lelystad", "Nijmegen", "Arnhem", "Utrecht", "Amsterdam", "Haarlem", "Den Helder", "'s-Gravenhage", "Rotterdam", "Dordrecht", "Leiden", "Middelburg", "Tilburg", "'s-Hertogenbosch", "Maastricht", "Bonaire"], "naam": "Daan de Neef", "achternaam": "de Neef", "voorletters": "D.", "voornaam": "Daan", "geslacht": "m", "stad": "Breda", "partij_naam": "VVD", "tweede_poging": false, "vorige_partij": ""}, "Jan Klink": {"lijstnummer": 35, "kieskringen": ["Groningen", "Leeuwarden", "Assen", "Zwolle", "Lelystad", "Nijmegen", "Arnhem", "Utrecht", "Amsterdam", "Haarlem", "Den Helder", "'s-Gravenhage", "Rotterdam", "Dordrecht", "Leiden", "Middelburg", "Tilburg", "'s-Hertogenbosch", "Maastricht", "Bonaire"], "naam": "Jan Klink", "achternaam": "Klink", "voorletters": "J.J.", "voornaam": "Jan", "geslacht": "m", "stad": "Loosdrecht", "partij_naam": "VVD", "tweede_poging": false, "vorige_partij": ""}, "Kelly Regterschot": {"lijstnummer": 36, "kieskringen": ["Groningen", "Leeuwarden", "Assen", "Zwolle", "Lelystad", "Nijmegen", "Arnhem", "Utrecht", "Amsterdam", "Haarlem", "Den Helder", "'s-Gravenhage", "Rotterdam", "Dordrecht", "Leiden", "Middelburg", "Tilburg", "'s-Hertogenbosch", "Maastricht", "Bonaire"], "naam": "Kelly Regterschot", "achternaam": "Regterschot", "voorletters": "K.", "voornaam": "Kelly", "geslacht": "v", "stad": "Landgraaf", "partij_naam": "VVD", "tweede_poging": true, "vorige_partij": ""}, "Bart Smals": {"lijstnummer": 37, "kieskringen": ["Groningen", "Leeuwarden", "Assen", "Zwolle", "Lelystad", "Nijmegen", "Arnhem", "Utrecht", "Amsterdam", "Haarlem", "Den Helder", "'s-Gravenhage", "Rotterdam", "Dordrecht", "Leiden", "Middelburg", "Tilburg", "'s-Hertogenbosch", "Maastricht", "Bonaire"], "naam": "Bart Smals", "achternaam": "Smals", "voorletters": "B.M.G.", "voornaam": "Bart", "geslacht": "m", "stad": "Delft", "partij_naam": "VVD", "tweede_poging": true, "vorige_partij": ""}, "Mark Strolenberg": {"lijstnummer": 38, "kieskringen": ["Groningen", "Leeuwarden", "Assen", "Zwolle", "Lelystad", "Nijmegen", "Arnhem", "Utrecht", "Amsterdam", "Haarlem", "Den Helder", "'s-Gravenhage", "Rotterdam", "Dordrecht", "Leiden", "Middelburg", "Tilburg", "'s-Hertogenbosch", "Maastricht", "Bonaire"], "naam": "Mark Strolenberg", "achternaam": "Strolenberg", "voorletters": "M.F.", "voornaam": "Mark", "geslacht": "m", "stad": "Hoogeveen", "partij_naam": "VVD", "tweede_poging": false, "vorige_partij": ""}, "Ruud Verkuijlen": {"lijstnummer": 39, "kieskringen": ["Groningen", "Leeuwarden", "Assen", "Zwolle", "Lelystad", "Nijmegen", "Arnhem", "Utrecht", "Amsterdam", "Haarlem", "Den Helder", "'s-Gravenhage", "Rotterdam", "Dordrecht", "Leiden", "Middelburg", "Tilburg", "'s-Hertogenbosch", "Maastricht", "Bonaire"], "naam": "Ruud Verkuijlen", "achternaam": "Verkuijlen", "voorletters": "R.", "voornaam": "Ruud", "geslacht": "m", "stad": "Hilversum", "partij_naam": "VVD", "tweede_poging": false, "vorige_partij": ""}, "Erik Haverkort": {"lijstnummer": 40, "kieskringen": ["Groningen", "Leeuwarden", "Assen", "Zwolle", "Lelystad", "Nijmegen", "Arnhem", "Utrecht", "Amsterdam", "Haarlem", "Den Helder", "'s-Gravenhage", "Rotterdam", "Dordrecht", "Leiden", "Middelburg", "Tilburg", "'s-Hertogenbosch", "Maastricht", "Bonaire"], "naam": "Erik Haverkort", "achternaam": "Haverkort", "voorletters": "E.A.", "voornaam": "Erik", "geslacht": "m", "stad": "Eefde", "partij_naam": "VVD", "tweede_poging": false, "vorige_partij": ""}, "Marinus Tabak": {"lijstnummer": 41, "kieskringen": ["Groningen", "Leeuwarden", "Assen", "Zwolle", "Lelystad", "Nijmegen", "Arnhem", "Utrecht", "Amsterdam", "Haarlem", "Den Helder", "'s-Gravenhage", "Rotterdam", "Dordrecht", "Leiden", "Middelburg", "Tilburg", "'s-Hertogenbosch", "Maastricht", "Bonaire"], "naam": "Marinus Tabak", "achternaam": "Tabak", "voorletters": "M.J.A.", "voornaam": "Marinus", "geslacht": "m", "stad": "Groningen", "partij_naam": "VVD", "tweede_poging": false, "vorige_partij": ""}, "Dorien Verbree": {"lijstnummer": 42, "kieskringen": ["Groningen", "Leeuwarden", "Assen", "Zwolle", "Lelystad", "Nijmegen", "Arnhem", "Utrecht", "Amsterdam", "Haarlem", "Den Helder", "'s-Gravenhage", "Rotterdam", "Dordrecht", "Leiden", "Middelburg", "Tilburg", "'s-Hertogenbosch", "Maastricht", "Bonaire"], "naam": "Dorien Verbree", "achternaam": "Verbree", "voorletters": "D.M.", "voornaam": "Dorien", "geslacht": "v", "stad": "Leiden", "partij_naam": "VVD", "tweede_poging": false, "vorige_partij": ""}, "Harry Bevers": {"lijstnummer": 43, "kieskringen": ["Groningen", "Leeuwarden", "Assen", "Zwolle", "Lelystad", "Nijmegen", "Arnhem", "Utrecht", "Amsterdam", "Haarlem", "Den Helder", "'s-Gravenhage", "Rotterdam", "Dordrecht", "Leiden", "Middelburg", "Tilburg", "'s-Hertogenbosch", "Maastricht", "Bonaire"], "naam": "Harry Bevers", "achternaam": "Bevers", "voorletters": "H.", "voornaam": "Harry", "geslacht": "m", "stad": "Leeuwarden", "partij_naam": "VVD", "tweede_poging": true, "vorige_partij": ""}, "Hawre Rahimi": {"lijstnummer": 44, "kieskringen": ["Groningen", "Leeuwarden", "Assen", "Zwolle", "Lelystad", "Nijmegen", "Arnhem", "Utrecht", "Amsterdam", "Haarlem", "Den Helder", "'s-Gravenhage", "Rotterdam", "Dordrecht", "Leiden", "Middelburg", "Tilburg", "'s-Hertogenbosch", "Maastricht", "Bonaire"], "naam": "Hawre Rahimi", "achternaam": "Rahimi", "voorletters": "H.", "voornaam": "Hawre", "geslacht": "m", "stad": "Weesp", "partij_naam": "VVD", "tweede_poging": false, "vorige_partij": ""}, "Martijn Grevink": {"lijstnummer": 45, "kieskringen": ["Groningen", "Leeuwarden", "Assen", "Zwolle", "Lelystad", "Nijmegen", "Arnhem", "Utrecht", "Amsterdam", "Haarlem", "Den Helder", "'s-Gravenhage", "Rotterdam", "Dordrecht", "Leiden", "Middelburg", "Tilburg", "'s-Hertogenbosch", "Maastricht", "Bonaire"], "naam": "Martijn Grevink", "achternaam": "Grevink", "voorletters": "M.", "voornaam": "Martijn", "geslacht": "m", "stad": "Elsene (Brussel) (BE)", "partij_naam": "VVD", "tweede_poging": false, "vorige_partij": ""}, "Chris Simons": {"lijstnummer": 46, "kieskringen": ["Groningen", "Leeuwarden", "Assen", "Zwolle", "Lelystad", "Nijmegen", "Arnhem", "Utrecht", "Amsterdam", "Haarlem", "Den Helder", "'s-Gravenhage", "Rotterdam", "Dordrecht", "Leiden", "Middelburg", "Tilburg", "'s-Hertogenbosch", "Maastricht", "Bonaire"], "naam": "Chris Simons", "achternaam": "Simons", "voorletters": "C.", "voornaam": "Chris", "geslacht": "m", "stad": "Middelburg", "partij_naam": "VVD", "tweede_poging": false, "vorige_partij": ""}, "Simone Richardson": {"lijstnummer": 47, "kieskringen": ["Groningen", "Leeuwarden", "Assen", "Zwolle", "Lelystad", "Nijmegen", "Arnhem", "Utrecht", "Amsterdam", "Haarlem", "Den Helder", "'s-Gravenhage", "Rotterdam", "Dordrecht", "Leiden", "Middelburg", "Tilburg", "'s-Hertogenbosch", "Maastricht", "Bonaire"], "naam": "Simone Richardson", "achternaam": "Richardson", "voorletters": "S.M.", "voornaam": "Simone", "geslacht": "v", "stad": "Lijnden", "partij_naam": "VVD", "tweede_poging": false, "vorige_partij": ""}, "Yvonne Bijenhof": {"lijstnummer": 48, "kieskringen": ["Groningen", "Leeuwarden", "Assen", "Zwolle", "Lelystad", "Nijmegen", "Arnhem", "Utrecht", "Amsterdam", "Haarlem", "Den Helder", "'s-Gravenhage", "Rotterdam", "Dordrecht", "Leiden", "Middelburg", "Tilburg", "'s-Hertogenbosch", "Maastricht", "Bonaire"], "naam": "Yvonne Bijenhof", "achternaam": "Bijenhof", "voorletters": "Y.", "voornaam": "Yvonne", "geslacht": "v", "stad": "Almelo", "partij_naam": "VVD", "tweede_poging": false, "vorige_partij": ""}, "Max Patelski": {"lijstnummer": 49, "kieskringen": ["Groningen", "Leeuwarden", "Assen", "Zwolle", "Lelystad", "Nijmegen", "Arnhem", "Utrecht", "Amsterdam", "Haarlem", "Den Helder", "'s-Gravenhage", "Rotterdam", "Dordrecht", "Leiden", "Middelburg", "Tilburg", "'s-Hertogenbosch", "Maastricht", "Bonaire"], "naam": "Max Patelski", "achternaam": "Patelski", "voorletters": "M.J.L.", "voornaam": "Max", "geslacht": "m", "stad": "Maastricht", "partij_naam": "VVD", "tweede_poging": false, "vorige_partij": ""}, "Kathy Arends-Drijver": {"lijstnummer": 50, "kieskringen": ["Groningen", "Leeuwarden", "Assen", "Zwolle", "Lelystad", "Nijmegen", "Arnhem", "Utrecht", "Amsterdam", "Haarlem", "Den Helder", "'s-Gravenhage", "Rotterdam", "Dordrecht", "Leiden", "Middelburg", "Tilburg", "'s-Hertogenbosch", "Maastricht", "Bonaire"], "naam": "Kathy Arends-Drijver", "achternaam": "Arends-Drijver", "voorletters": "K.", "voornaam": "Kathy", "geslacht": "v", "stad": "Berkel en Rodenrijs", "partij_naam": "VVD", "tweede_poging": true, "vorige_partij": ""}, "Laurens van Doeveren": {"lijstnummer": 51, "kieskringen": ["Groningen", "Leeuwarden", "Assen", "Zwolle", "Lelystad", "Nijmegen", "Arnhem", "Utrecht", "Amsterdam", "Haarlem", "Den Helder", "'s-Gravenhage", "Rotterdam", "Dordrecht", "Leiden", "Middelburg", "Tilburg", "'s-Hertogenbosch", "Maastricht", "Bonaire"], "naam": "Laurens van Doeveren", "achternaam": "van Doeveren", "voorletters": "L.N.M.", "voornaam": "Laurens", "geslacht": "m", "stad": "Wassenaar", "partij_naam": "VVD", "tweede_poging": false, "vorige_partij": ""}, "Tim Simons": {"lijstnummer": 52, "kieskringen": ["Groningen", "Leeuwarden", "Assen", "Zwolle", "Lelystad", "Nijmegen", "Arnhem", "Utrecht", "Amsterdam", "Haarlem", "Den Helder", "'s-Gravenhage", "Rotterdam", "Dordrecht", "Leiden", "Middelburg", "Tilburg", "'s-Hertogenbosch", "Maastricht", "Bonaire"], "naam": "Tim Simons", "achternaam": "Simons", "voorletters": "T.C.N.", "voornaam": "Tim", "geslacht": "m", "stad": "Made", "partij_naam": "VVD", "tweede_poging": false, "vorige_partij": ""}, "Martijn Buijsse": {"lijstnummer": 53, "kieskringen": ["Groningen", "Leeuwarden", "Assen", "Zwolle", "Lelystad", "Nijmegen", "Arnhem", "Utrecht", "Amsterdam", "Haarlem", "Den Helder", "'s-Gravenhage", "Rotterdam", "Dordrecht", "Leiden", "Middelburg", "Tilburg", "'s-Hertogenbosch", "Maastricht", "Bonaire"], "naam": "Martijn Buijsse", "achternaam": "Buijsse", "voorletters": "M.R.G.", "voornaam": "Martijn", "geslacht": "m", "stad": "Boekel", "partij_naam": "VVD", "tweede_poging": false, "vorige_partij": ""}, "Frederik Peters": {"lijstnummer": 54, "kieskringen": ["Groningen", "Leeuwarden", "Assen", "Zwolle", "Lelystad", "Nijmegen", "Arnhem", "Utrecht", "Amsterdam", "Haarlem", "Den Helder", "'s-Gravenhage", "Rotterdam", "Dordrecht", "Leiden", "Middelburg", "Tilburg", "'s-Hertogenbosch", "Maastricht", "Bonaire"], "naam": "Frederik Peters", "achternaam": "Peters", "voorletters": "F.A.J.", "voornaam": "Frederik", "geslacht": "m", "stad": "Lent", "partij_naam": "VVD", "tweede_poging": false, "vorige_partij": ""}, "Ronald Bakker": {"lijstnummer": 55, "kieskringen": ["Groningen", "Leeuwarden", "Assen", "Zwolle", "Lelystad", "Nijmegen", "Arnhem", "Utrecht", "Amsterdam", "Haarlem", "Den Helder", "'s-Gravenhage", "Rotterdam", "Dordrecht", "Leiden", "Middelburg", "Tilburg", "'s-Hertogenbosch", "Maastricht", "Bonaire"], "naam": "Ronald Bakker", "achternaam": "Bakker", "voorletters": "R.", "voornaam": "Ronald", "geslacht": "m", "stad": "Sprang-Capelle", "partij_naam": "VVD", "tweede_poging": false, "vorige_partij": ""}, "Kees Noomen": {"lijstnummer": 56, "kieskringen": ["Groningen", "Leeuwarden", "Assen", "Zwolle", "Lelystad", "Nijmegen", "Arnhem", "Utrecht", "Amsterdam", "Haarlem", "Den Helder", "'s-Gravenhage", "Rotterdam", "Dordrecht", "Leiden", "Middelburg", "Tilburg", "'s-Hertogenbosch", "Maastricht", "Bonaire"], "naam": "Kees Noomen", "achternaam": "Noomen", "voorletters": "C.J.", "voornaam": "Kees", "geslacht": "m", "stad": "Amstelveen", "partij_naam": "VVD", "tweede_poging": false, "vorige_partij": ""}, "Sanneke Vermeulen": {"lijstnummer": 57, "kieskringen": ["Groningen", "Leeuwarden", "Assen", "Zwolle", "Lelystad", "Nijmegen", "Arnhem", "Utrecht", "Amsterdam", "Haarlem", "Den Helder", "'s-Gravenhage", "Rotterdam", "Dordrecht", "Leiden", "Middelburg", "Tilburg", "'s-Hertogenbosch", "Maastricht", "Bonaire"], "naam": "Sanneke Vermeulen", "achternaam": "Vermeulen", "voorletters": "S.M.J.", "voornaam": "Sanneke", "geslacht": "v", "stad": "Roosendaal", "partij_naam": "VVD", "tweede_poging": false, "vorige_partij": ""}, "Sabine Koebrugge": {"lijstnummer": 58, "kieskringen": ["Groningen", "Leeuwarden", "Assen", "Zwolle", "Lelystad", "Nijmegen", "Arnhem", "Utrecht", "Amsterdam", "Haarlem", "Den Helder", "'s-Gravenhage", "Rotterdam", "Dordrecht", "Leiden", "Middelburg", "Tilburg", "'s-Hertogenbosch", "Maastricht", "Bonaire"], "naam": "Sabine Koebrugge", "achternaam": "Koebrugge", "voorletters": "S.A.", "voornaam": "Sabine", "geslacht": "v", "stad": "Groningen", "partij_naam": "VVD", "tweede_poging": false, "vorige_partij": ""}, "Mark Achterbergh-Copier": {"lijstnummer": 59, "kieskringen": ["Groningen", "Leeuwarden", "Assen", "Zwolle", "Lelystad", "Nijmegen", "Arnhem", "Utrecht", "Amsterdam", "Haarlem", "Den Helder", "'s-Gravenhage", "Rotterdam", "Dordrecht", "Leiden", "Middelburg", "Tilburg", "'s-Hertogenbosch", "Maastricht", "Bonaire"], "naam": "Mark Achterbergh-Copier", "achternaam": "Achterbergh-Copier", "voorletters": "M.", "voornaam": "Mark", "geslacht": "m", "stad": "Halfweg", "partij_naam": "VVD", "tweede_poging": false, "vorige_partij": ""}, "Jenny Elbertsen": {"lijstnummer": 60, "kieskringen": ["Groningen", "Leeuwarden", "Assen", "Zwolle", "Lelystad", "Nijmegen", "Arnhem", "Utrecht", "Amsterdam", "Haarlem", "Den Helder", "'s-Gravenhage", "Rotterdam", "Dordrecht", "Leiden", "Middelburg", "Tilburg", "'s-Hertogenbosch", "Maastricht", "Bonaire"], "naam": "Jenny Elbertsen", "achternaam": "Elbertsen", "voorletters": "J.", "voornaam": "Jenny", "geslacht": "v", "stad": "Apeldoorn", "partij_naam": "VVD", "tweede_poging": true, "vorige_partij": ""}, "Barry Jacobs": {"lijstnummer": 61, "kieskringen": ["Groningen", "Leeuwarden", "Assen", "Zwolle", "Lelystad", "Nijmegen", "Arnhem", "Utrecht", "Amsterdam", "Haarlem", "Den Helder", "'s-Gravenhage", "Rotterdam", "Dordrecht", "Leiden", "Middelburg", "Tilburg", "'s-Hertogenbosch", "Maastricht", "Bonaire"], "naam": "Barry Jacobs", "achternaam": "Jacobs", "voorletters": "B.", "voornaam": "Barry", "geslacht": "m", "stad": "Bergen op Zoom", "partij_naam": "VVD", "tweede_poging": true, "vorige_partij": ""}, "Saskia van Dijk": {"lijstnummer": 62, "kieskringen": ["Groningen", "Leeuwarden", "Assen", "Zwolle", "Lelystad", "Nijmegen", "Arnhem", "Utrecht", "Amsterdam", "Haarlem", "Den Helder", "'s-Gravenhage", "Rotterdam", "Dordrecht", "Leiden", "Middelburg", "Tilburg", "'s-Hertogenbosch", "Maastricht", "Bonaire"], "naam": "Saskia van Dijk", "achternaam": "van Dijk", "voorletters": "S.", "voornaam": "Saskia", "geslacht": "v", "stad": "IJsselstein", "partij_naam": "VVD", "tweede_poging": true, "vorige_partij": ""}, "Hugo Bellaart": {"lijstnummer": 63, "kieskringen": ["Groningen", "Leeuwarden", "Assen", "Zwolle", "Lelystad", "Nijmegen", "Arnhem", "Utrecht", "Amsterdam", "Haarlem", "Den Helder", "'s-Gravenhage", "Rotterdam", "Dordrecht", "Leiden", "Middelburg", "Tilburg", "'s-Hertogenbosch", "Maastricht", "Bonaire"], "naam": "Hugo Bellaart", "achternaam": "Bellaart", "voorletters": "H.M.", "voornaam": "Hugo", "geslacht": "m", "stad": "Bussum", "partij_naam": "VVD", "tweede_poging": false, "vorige_partij": ""}, "Rebin Maref": {"lijstnummer": 64, "kieskringen": ["Groningen", "Leeuwarden", "Assen", "Zwolle", "Lelystad", "Nijmegen", "Arnhem", "Utrecht", "Amsterdam", "Haarlem", "Den Helder", "'s-Gravenhage", "Rotterdam", "Dordrecht", "Leiden", "Middelburg", "Tilburg", "'s-Hertogenbosch", "Maastricht", "Bonaire"], "naam": "Rebin Maref", "achternaam": "Maref", "voorletters": "R.", "voornaam": "Rebin", "geslacht": "m", "stad": "Arnhem", "partij_naam": "VVD", "tweede_poging": false, "vorige_partij": ""}, "Ivo de Wolff": {"lijstnummer": 65, "kieskringen": ["Groningen", "Leeuwarden", "Assen", "Zwolle", "Lelystad", "Nijmegen", "Arnhem", "Utrecht", "Amsterdam", "Haarlem", "Den Helder", "'s-Gravenhage", "Rotterdam", "Dordrecht", "Leiden", "Middelburg", "Tilburg", "'s-Hertogenbosch", "Maastricht", "Bonaire"], "naam": "Ivo de Wolff", "achternaam": "de Wolff", "voorletters": "I.", "voornaam": "Ivo", "geslacht": "m", "stad": "Sint Nicolaasga", "partij_naam": "VVD", "tweede_poging": false, "vorige_partij": ""}, "Laurence Groot Bruinderink": {"lijstnummer": 66, "kieskringen": ["Groningen", "Leeuwarden", "Assen", "Zwolle", "Lelystad", "Nijmegen", "Arnhem", "Utrecht", "Amsterdam", "Haarlem", "Den Helder", "'s-Gravenhage", "Rotterdam", "Dordrecht", "Leiden", "Middelburg", "Tilburg", "'s-Hertogenbosch", "Maastricht", "Bonaire"], "naam": "Laurence Groot Bruinderink", "achternaam": "Groot Bruinderink", "voorletters": "L.I.", "voornaam": "Laurence", "geslacht": "m", "stad": "New York (US)", "partij_naam": "VVD", "tweede_poging": false, "vorige_partij": ""}, "Lars Lambers": {"lijstnummer": 67, "kieskringen": ["Groningen", "Leeuwarden", "Assen", "Zwolle", "Lelystad", "Nijmegen", "Arnhem", "Utrecht", "Amsterdam", "Haarlem", "Den Helder", "'s-Gravenhage", "Rotterdam", "Dordrecht", "Leiden", "Middelburg", "Tilburg", "'s-Hertogenbosch", "Maastricht", "Bonaire"], "naam": "Lars Lambers", "achternaam": "Lambers", "voorletters": "L.F.J.M.", "voornaam": "Lars", "geslacht": "m", "stad": "Weert", "partij_naam": "VVD", "tweede_poging": false, "vorige_partij": ""}, "Laurine Bonnevits-de Jong": {"lijstnummer": 68, "kieskringen": ["Groningen", "Leeuwarden", "Assen", "Zwolle", "Lelystad", "Nijmegen", "Arnhem", "Utrecht", "Amsterdam", "Haarlem", "Den Helder", "'s-Gravenhage", "Rotterdam", "Dordrecht", "Leiden", "Middelburg", "Tilburg", "'s-Hertogenbosch", "Maastricht", "Bonaire"], "naam": "Laurine Bonnevits-de Jong", "achternaam": "Bonnevits-de Jong", "voorletters": "L.", "voornaam": "Laurine", "geslacht": "v", "stad": "Berkel en Rodenrijs", "partij_naam": "VVD", "tweede_poging": true, "vorige_partij": ""}, "Mirjam Nelisse": {"lijstnummer": 69, "kieskringen": ["Groningen", "Leeuwarden", "Assen", "Zwolle", "Lelystad", "Nijmegen", "Arnhem", "Utrecht", "Amsterdam", "Haarlem", "Den Helder", "'s-Gravenhage", "Rotterdam", "Dordrecht", "Leiden", "Middelburg", "Tilburg", "'s-Hertogenbosch", "Maastricht", "Bonaire"], "naam": "Mirjam Nelisse", "achternaam": "Nelisse", "voorletters": "R.M.L.", "voornaam": "Mirjam", "geslacht": "v", "stad": "Dirksland", "partij_naam": "VVD", "tweede_poging": false, "vorige_partij": ""}, "Liesbeth Rooijmans": {"lijstnummer": 70, "kieskringen": ["Groningen", "Leeuwarden", "Assen", "Zwolle", "Lelystad", "Nijmegen", "Arnhem", "Utrecht", "Amsterdam", "Haarlem", "Den Helder", "'s-Gravenhage", "Rotterdam", "Dordrecht", "Leiden", "Middelburg", "Tilburg", "'s-Hertogenbosch", "Maastricht", "Bonaire"], "naam": "Liesbeth Rooijmans", "achternaam": "Rooijmans", "voorletters": "E.M.N.", "voornaam": "Liesbeth", "geslacht": "v", "stad": "Apeldoorn", "partij_naam": "VVD", "tweede_poging": false, "vorige_partij": ""}, "Sharona Malfait-van Ham": {"lijstnummer": 71, "kieskringen": ["Groningen", "Leeuwarden", "Assen", "Zwolle", "Lelystad", "Nijmegen", "Arnhem", "Utrecht", "Amsterdam", "Haarlem", "Den Helder", "'s-Gravenhage", "Rotterdam", "Dordrecht", "Leiden", "Middelburg", "Tilburg", "'s-Hertogenbosch", "Maastricht", "Bonaire"], "naam": "Sharona Malfait-van Ham", "achternaam": "Malfait-van Ham", "voorletters": "S.S.J.", "voornaam": "Sharona", "geslacht": "v", "stad": "Oud Gastel", "partij_naam": "VVD", "tweede_poging": false, "vorige_partij": ""}, "Ren\u00e9 ten Have": {"lijstnummer": 72, "kieskringen": ["Groningen", "Leeuwarden", "Assen", "Zwolle", "Lelystad", "Nijmegen", "Arnhem", "Utrecht", "Amsterdam", "Haarlem", "Den Helder", "'s-Gravenhage", "Rotterdam", "Dordrecht", "Leiden", "Middelburg", "Tilburg", "'s-Hertogenbosch", "Maastricht", "Bonaire"], "naam": "Ren\u00e9 ten Have", "achternaam": "ten Have", "voorletters": "R.H.", "voornaam": "Ren\u00e9", "geslacht": "m", "stad": "'s-Gravenhage", "partij_naam": "VVD", "tweede_poging": false, "vorige_partij": ""}, "Henk Matthijsse": {"lijstnummer": 73, "kieskringen": ["Groningen", "Leeuwarden", "Assen", "Zwolle", "Lelystad", "Nijmegen", "Arnhem", "Utrecht", "Amsterdam", "Haarlem", "Den Helder", "'s-Gravenhage", "Rotterdam", "Dordrecht", "Leiden", "Middelburg", "Tilburg", "'s-Hertogenbosch", "Maastricht", "Bonaire"], "naam": "Henk Matthijsse", "achternaam": "Matthijsse", "voorletters": "H.A.", "voornaam": "Henk", "geslacht": "m", "stad": "Assen", "partij_naam": "VVD", "tweede_poging": false, "vorige_partij": ""}, "R.T. Hoen": {"lijstnummer": 74, "kieskringen": ["Groningen", "Leeuwarden", "Assen", "Zwolle", "Lelystad", "Nijmegen", "Arnhem", "Utrecht", "Amsterdam", "Haarlem", "Den Helder", "'s-Gravenhage", "Rotterdam", "Dordrecht", "Leiden", "Middelburg", "Tilburg", "'s-Hertogenbosch", "Maastricht", "Bonaire"], "naam": "R.T. Hoen", "achternaam": "Hoen", "voorletters": "R.T.", "voornaam": "", "geslacht": "m", "stad": "Noordwolde", "partij_naam": "VVD", "tweede_poging": false, "vorige_partij": ""}, "Sander Janssen": {"lijstnummer": 75, "kieskringen": ["Groningen", "Leeuwarden", "Assen", "Zwolle", "Lelystad", "Nijmegen", "Arnhem", "Utrecht", "Amsterdam", "Haarlem", "Den Helder", "'s-Gravenhage", "Rotterdam", "Dordrecht", "Leiden", "Middelburg", "Tilburg", "'s-Hertogenbosch", "Maastricht", "Bonaire"], "naam": "Sander Janssen", "achternaam": "Janssen", "voorletters": "S.M.", "voornaam": "Sander", "geslacht": "m", "stad": "Hengelo", "partij_naam": "VVD", "tweede_poging": false, "vorige_partij": ""}, "Edith van den Ham-Jaarsma": {"lijstnummer": 76, "kieskringen": ["Groningen", "Leeuwarden", "Assen", "Zwolle", "Lelystad", "Nijmegen", "Arnhem", "Utrecht", "Amsterdam", "Haarlem", "Den Helder", "'s-Gravenhage", "Rotterdam", "Dordrecht", "Leiden", "Middelburg", "Tilburg", "'s-Hertogenbosch", "Maastricht", "Bonaire"], "naam": "Edith van den Ham-Jaarsma", "achternaam": "van den Ham-Jaarsma", "voorletters": "E.", "voornaam": "Edith", "geslacht": "v", "stad": "Almelo", "partij_naam": "VVD", "tweede_poging": false, "vorige_partij": ""}, "Filip Lauwerysen": {"lijstnummer": 77, "kieskringen": ["Groningen", "Leeuwarden", "Assen", "Zwolle", "Lelystad", "Nijmegen", "Arnhem", "Utrecht", "Amsterdam", "Haarlem", "Den Helder", "'s-Gravenhage", "Rotterdam", "Dordrecht", "Leiden", "Middelburg", "Tilburg", "'s-Hertogenbosch", "Maastricht", "Bonaire"], "naam": "Filip Lauwerysen", "achternaam": "Lauwerysen", "voorletters": "F.A.", "voornaam": "Filip", "geslacht": "m", "stad": "Grizane (HR)", "partij_naam": "VVD", "tweede_poging": false, "vorige_partij": ""}, "Bart Bikkers": {"lijstnummer": 78, "kieskringen": ["Groningen", "Leeuwarden", "Assen", "Zwolle", "Lelystad", "Nijmegen", "Arnhem", "Utrecht", "Amsterdam", "Haarlem", "Den Helder", "'s-Gravenhage", "Rotterdam", "Dordrecht", "Leiden", "Middelburg", "Tilburg", "'s-Hertogenbosch", "Maastricht", "Bonaire"], "naam": "Bart Bikkers", "achternaam": "Bikkers", "voorletters": "B.T.", "voornaam": "Bart", "geslacht": "m", "stad": "Vlaardingen", "partij_naam": "VVD", "tweede_poging": false, "vorige_partij": ""}, "Kees Kraanen": {"lijstnummer": 79, "kieskringen": ["Groningen", "Leeuwarden", "Assen", "Zwolle", "Lelystad", "Nijmegen", "Arnhem", "Utrecht", "Amsterdam", "Haarlem", "Den Helder", "'s-Gravenhage", "Rotterdam", "Dordrecht", "Leiden", "Middelburg", "Tilburg", "'s-Hertogenbosch", "Maastricht", "Bonaire"], "naam": "Kees Kraanen", "achternaam": "Kraanen", "voorletters": "C.W.", "voornaam": "Kees", "geslacht": "m", "stad": "Amersfoort", "partij_naam": "VVD", "tweede_poging": false, "vorige_partij": ""}, "Maarten van der Weijden": {"lijstnummer": 80, "kieskringen": ["Groningen", "Leeuwarden", "Assen", "Zwolle", "Lelystad", "Nijmegen", "Arnhem", "Utrecht", "Amsterdam", "Haarlem", "Den Helder", "'s-Gravenhage", "Rotterdam", "Dordrecht", "Leiden", "Middelburg", "Tilburg", "'s-Hertogenbosch", "Maastricht", "Bonaire"], "naam": "Maarten van der Weijden", "achternaam": "van der Weijden", "voorletters": "M.", "voornaam": "Maarten", "geslacht": "m", "stad": "Waspik", "partij_naam": "VVD", "tweede_poging": true, "vorige_partij": ""}}